Workbook

Sheet Summary
A1: Accountant Pack — Lakeside Painting Limited
A2: Period 19 January 2026 to 31 July 2026 · all amounts NZD · NZ GST 15% · prepared from the Gmail mailbox and the TradePilot export
A4: HEADLINE FIGURES
A5: Customer invoices issued (sales)
A6: Total excluding GST | C6: ='Customer Invoices'!G44 -> 58913.37
A7: GST | C7: ='Customer Invoices'!H44 -> 8837.01
A8: Total including GST | C8: ='Customer Invoices'!I44 -> 67750.38
A9: of which confirmed paid | C9: ='Customer Invoices'!I47 -> 26078.08
A10: payment not confirmed | C10: ='Customer Invoices'!I48 -> 41672.3
A12: Supplier bills & receipts (purchases)
A13: Total excluding GST | C13: ='Supplier Bills'!F82 -> 15524.27
A14: GST | C14: ='Supplier Bills'!G82 -> 2328.68
A15: Total including GST | C15: ='Supplier Bills'!H82 -> 17852.96
A17: Net GST position (output less input GST) | C17: =C7-C14 -> 6508.33
A18: Gross margin before overheads not in email | C18: =C6-C13 -> 43389.1
A19: These totals are provisional. Read the two sections below before relying on them.
A21: HOW COMPLETE IS THIS?
A22: Item | C22: Count | D22: Note
A23: Customer invoices found | C23: 37 | D23: 36 have a figure; 1 (INV-028-Final, 10 McLeod Ave) does not — its PDF could not be retrieved.
A24: with amounts verified from the source document | C24: see tab | D24: Column J on the Customer Invoices tab marks each one. Amber = derived, not read.
A25: Supplier bills found | C25: 75 | D25: Dulux 33, Resene 8, Trademax 15 + 2 credits, everything else 17.
A26: Supplier statements reconciled | C26: 13 | D26: Dulux and Trademax reconcile month by month. See the Supplier Statements tab.
A27: Categories with NO records at all | C27: 7 | D27: Fuel, phone/internet, ACC, bank fees, vehicle, professional fees, and software beyond Google Workspace.
A28: Period covered by the TradePilot export | C28: 18 Jan – 9 Apr | D28: After 9 April the only source is email. The export is also labelled "Sandbox".
A30: READ THIS BEFORE BOOKING ANYTHING
A31: ▸ The GST registration date is unresolved.
A32: An IRD letter of 14 May 2026 says information requested for backdating the GST registration was not provided. Until that is settled from myIR, every GST figure here is provisional.
A34: ▸ Up to $2,907.14 of Dulux cost may not be real.
A35: Two identical $1,453.57 invoices for the same purchase order, neither properly settled and no credit note issued. Confirm with Dulux first.
A37: ▸ One invoice was issued with GST charged twice.
A38: 7 Cairnmuir St (Home & Co): deposit INV-8836EB $686.38 and final INV-Q040 first issued at $1,601.54, corrected the same day to $1,303.12. If the ledger holds the $1,601.54 version, income is overstated by $259.50 and GST by $38.92.
A40: ▸ One invoice went out with a dead bank account.
A41: Central Lakes Equestrian Club INV-034-DEP carried a stale ANZ number from an old template; the Treasurer's $1,794 payment was rejected. Corrected to BNZ on 27 May, but no successful payment is confirmed for either that or the $4,186 final.
A43: ▸ A $5,057.70 deposit invoice should be voided.
A44: 3 Parkview Street (Kevin Henderson): the job was cancelled on 19 May when the house sold, before any work. Never paid, no credit note. It is not income.
A46: ▸ Some costs were paid personally or by personal card.
... A52: WHAT IS IN THIS WORKBOOK
A53: Customer Invoices | B53: Every invoice Lakeside issued in the period, with GST split, payment date and status, and where each figure came from.
A54: Supplier Bills | B54: Every supplier bill and receipt, categorised, with GST split, payment status and how it was paid. Category subtotals at the bottom.
A55: Credit Notes & Adjustments | B55: Credit notes, refunds, re-issued invoices, cancellations, price reductions and doubtful debts. Read this before the two tabs above.
A56: Gaps & Follow-ups | B56: What is missing from the record, prioritised, with where to get it.
A57: Supplier Statements | B57: Dulux, Resene and Trademax statements for reconciling the Supplier Bills tab.
A59: Sources: Gmail (lakesidepaintinglimited@gmail.com / info@lakesidepainting.co.nz), including PDF attachments read directly; and the TradePilot export at Desktop/lakeside-painting/TradePilot/data/import (18 Jan – 9 Apr 2026).

Sheet Customer Invoices
A1: Customer Invoices Issued
A2: Lakeside Painting Limited · 19 Jan – 31 Jul 2026 · all amounts NZD · GST 15%
A5: Invoice date | B5: Invoice no. | C5: Customer | D5: Company | E5: Job / address | F5: Type | G5: Amount ex GST | H5: GST | I5: Total incl GST | J5: Amount verified? | K5: Source of figures | L5: Payment date | M5: Payment status | N5: Evidence / notes | O5: Gmail thread
A6: 2026-01-19 | B6: — | C6: Craig Chirnside | E6: 18 Hewson Crescent, Lake Hawea - exterior cedar staining (2 coats Wattyl stain, client-supplied) | F6: Deposit | G6: 554 | H6: 83.1 | I6: 637.1 | J6: No | K6: email body | L6: 2026-01-19 | M6: Paid | N6: Customer replied same day: 'Paid. Thanks' (19 Jan 2026). Brad replied 'Thanks Craig'. | Email says only 'I've attached the 20% deposit invoice'. Attachment 'deposit-invoice.pdf' NOT opened. Amount DERIVED: accepted quote (3 Nov 2025) was $2,770 + GST = $3,185.50 incl; 20% = $637.10 incl. It is unclear whether the 20% was calculated on the GST-inclusive or GST-exclusive figure (20% of $2,770 ex = $554 ex / $637.10 incl - same result, so this derivation is reasonably safe). Invoice date assumed = email date. NEEDS THE PDF CHECKED. | O6: 19bd57c79838bcf3
A7: 2026-01-21 | B7: — | C7: Pennie Jackson | E7: Flat (Wanaka; access via son Jonty Jackson) - interior refresh repaint | F7: Deposit | G7: 1440 | H7: 216 | I7: 1656 | J7: No | K7: email body | L7: 2026-01-21 | M7: Paid | N7: Pennie 22 Jan 2026 (NZ time 21 Jan UTC): 'I just paid the deposit. See bank receipt attached.' Brad: 'Thanks for confirming the deposit, I've received it.' | Email says '30% deposit invoice'; PDF 'Pennies deposit invoice - Invoice.pdf' NOT opened. Amount DERIVED from accepted revised quote stated in the thread: $4,800 + GST ($720) = $5,520 incl; 30% = $1,656 incl. NEEDS THE PDF CHECKED. | O7: 19c2cc1bacc2b673
A8: 2026-01-26 | B8: — | C8: Sarah Brand and George Ferguson | E8: Lake Hawea - powder room wallpaper installation (final balance after deposit) | F8: Final | G8: 657.35 | H8: 98.6 | I8: 755.95 | J8: Yes | K8: PDF read | L8: 2026-01-28 | M8: Paid | N8: Sarah Brand 28 Jan 2026: 'We have just paid the balance of the invoice now - paid from ANZ account.' Brad 28 Jan: 'Thanks very much for the prompt payment.' | PDF attached ('Lake Hawea Powder Room - Invoice.pdf'), figures NOT in body and no quote figure appears anywhere in the mailbox for this job - NEEDS THE PDF CHECKED. The related deposit invoice was emailed 16 Jan 2026 (thread 19be747efeb52c44), which is BEFORE the 19 Jan period start, so it is excluded here. | O8: 19c08a68be2cdc76
A9: 2026-01-30 | B9: — | C9: Craig Chirnside | E9: 18 Hewson Crescent, Lake Hawea - exterior cedar staining, final balance | F9: Final | G9: 1916 | H9: 287.4 | I9: 2203.4 | J9: No | K9: email body | L9: 2026-01-30 | M9: Paid | N9: Customer 30 Jan 2026: 'Paid and gave you a 5 star review.' Brad 30 Jan: 'payment received - appreciate the quick turnaround.' | Scaffold line item removed: 'We ended up not needing the scaffold so I've taken that $300 off the original quote.' Job total reduced from $2,770 + GST to $2,470 + GST. | Attachment 'Craig Exterior Staining Final Invoice - Invoice.pdf' NOT opened; no figures in body. Amount DERIVED: revised job total $2,470 + GST = $2,840.50 incl, less deposit $637.10 = $2,203.40 incl. NEEDS THE PDF CHECKED - the deposit may have been credited on a different basis. | O9: 19c11262ee4ac497
A10: 2026-02-02 | B10: — | C10: Troy Nicholson | E10: 4 Perrow Street, Wanaka - painting of fibre cement gables | F10: Deposit | G10: 405 | H10: 60.75 | I10: 465.75 | J10: Yes | K10: PDF read | L10: 2026-02-02 | M10: Paid | N10: Troy 2 Feb 2026: 'Thank you, paid now and good to go.' | PDF 'Deposit for Fiber Cement Gables - Invoice.pdf' NOT opened. Body gives NO deposit amount and NO deposit percentage, so no reliable derivation is possible. Total job price quoted in the same thread was $1,350 + GST = $1,552.50 incl. NEEDS THE PDF CHECKED. | O10: 19c1d5873ca4f067
A11: 2026-02-08 | B11: — | C11: Pennie Jackson | E11: Flat (Wanaka) - interior refresh repaint, final balance | F11: Final | G11: 3360 | H11: 504 | I11: 3864 | J11: No | K11: email body | L11: 2026-02-08 | M11: Paid | N11: Pennie 8 Feb 2026: 'Please find bank receipt attached and again thanks so much.' | Scope overran (5 days on site vs 3 quoted, extra prep, 2 coats on ceilings/woodwork). Lakeside absorbed the extra: 'We're happy to honour the last quoted price though.' No variation charged. | PDF 'Pennies final invoice - Invoice.pdf' NOT opened. Amount DERIVED: quoted total $5,520 incl held, less 30% deposit $1,656 = $3,864 incl. NEEDS THE PDF CHECKED. | O11: 19c3c30d857d05c6
A12: 2026-02-15 | B12: — | C12: Troy Nicholson | E12: 4 Perrow Street, Wanaka - gables, final balance | F12: Final | G12: 945.22 | H12: 141.78 | I12: 1087 | J12: No | K12: Owner's ledger (Business Data workbook) - invoice PDF unreadable | L12: 2026-02-15 | M12: Paid | N12: Troy 15 Feb 2026: 'Have paid remainder now.' Brad same day: 'payment received - much appreciated.' | PDF '4 Perrow St - Final Invoice - Invoice.pdf' NOT opened; no figures in body. Balance cannot be derived because the deposit amount is unknown. Job total was $1,350 + GST = $1,552.50 incl. NEEDS THE PDF CHECKED. | O12: 19c5fcf2d1381c66
A13: 2026-02-19 | B13: — | C13: Liam | D13: LC Decorating (liam@lcdecorating.co.nz) | E13: Not stated in email. Likely subcontract decorating work. | F13: Other | G13: 360 | H13: 54 | I13: 414 | J13: Yes | K13: PDF read | M13: Unknown | N13: No reply and no payment reference anywhere in the mailbox. | HIGH PRIORITY GAP. Subject is just 'invoice', the email body is completely EMPTY, and the only content is the attachment 'Invoice for Liam - Invoice.pdf'. No amount, no job address, no payment evidence. NEEDS THE PDF CHECKED and payment status confirmed against the bank. | O13: 19c74494ddf23ba7
A14: 2026-02-21 | B14: — | C14: Hilary Waller | E14: Wanaka holiday property - decks clean and oil, pergola columns, exterior window frames, front door reseal | F14: Deposit | G14: 852.17 | H14: 127.83 | I14: 980 | J14: Yes | K14: email body | L14: 2026-02-21 | M14: Paid | N14: Hilary 21 Feb 2026: 'Thank you Brad deposit paid'. Brad same day: 'Thanks Hilary, deposit received!' | AMBIGUITY: body states 'an invoice for a 20% deposit ($980)' but does not say whether $980 is GST-inclusive or GST-exclusive. Treated here as GST-INCLUSIVE (ex $852.17 / GST $127.83). Note the quote was $4,250 + GST = $4,887.50 incl, and 20% of that is $977.50 - close to but NOT equal to $980, so the $980 may be 20% of a rounded figure or may be ex-GST ($980 + GST = $1,127). NEEDS THE PDF CHECKED. | O14: 19c91c156d15ab53
A15: 2026-02-23 | B15: — | C15: Danya Meakins | E15: 56 Dale Street - living/dining/kitchen ceiling repaint (49 sqm) | F15: Deposit | G15: 256 | H15: 38.4 | I15: 294.4 | J15: Yes | K15: PDF read | L15: 2026-02-24 | M15: Paid | N15: Danya 25 Feb 2026 NZ (24 Feb UTC): 'We have paid the deposit as requested, please find attached payment confirmation.' | PDF '56 Dale Street - Invoice.pdf' NOT opened. Body confirms the JOB price ($1,280 + GST = $1,472 incl) but gives NO deposit amount or percentage, so the deposit cannot be derived. NEEDS THE PDF CHECKED. | O15: 19ca0e8c609f737b
A16: 2026-02-25 | B16: — | C16: Sarah Gunn | E16: 50 Dale Street - cedar cladding clean/sand/2 coats stain + painted corner boards | F16: Progress | G16: 2320 | H16: 348 | I16: 2668 | J16: No | K16: email body | M16: Unknown | N16: Sarah Gunn 25 Feb 2026: 'We will put the payment through shortly.' No explicit confirmation of receipt for THIS invoice was found (Brad's later 'confirming the invoice has come through' on 5 Mar sits in the FINAL invoice thread). | Body states 'a progress invoice for 40%' and that 'The remaining balance (30%) will be due once the final paintwork is completed', implying a 30% deposit was raised earlier. PDF '50 dale street - progress payment invoice - Invoice.pdf' NOT opened. Amount DERIVED: quote $5,800 + GST = $6,670 incl; 40% = $2,668 incl. Sister Catherine Gunn (catherine@beweb.co.nz) is co | O16: 19c93a346fdf50d1
A17: 2026-02-27 | B17: — | C17: Glenda Turner | E17: 29 Tomtit Crescent, Lake Hawea - retaining wall wash + 3 coats Resene Lumbersider (FlaxPod) | F17: Deposit | G17: 294 | H17: 44.1 | I17: 338.1 | J17: No | K17: email body | L17: 2026-02-27 | M17: Paid | N17: Glenda 27 Feb 2026: 'I've just paid this and sent a separate email from Westpac showing proof of payment.' Brad 1 Mar: 'I've received the payment.' Receipt PDF emailed 5 Mar 2026. | Body says only '30% deposit invoice'. PDF 'Deposit for Glenda - Retaining Wall - Invoice.pdf' NOT opened. Amount DERIVED: quote $980 + GST = $1,127 incl; 30% = $338.10 incl. NEEDS THE PDF CHECKED. | O17: 19c9d7a4cab0e588
A18: 2026-03-02 | B18: — | C18: Sarah Gunn | E18: 50 Dale Street - final balance incl. replaced/painted rear corner boards | F18: Final | G18: 1740 | H18: 261 | I18: 2001 | J18: No | K18: email body | L18: 2026-03-05 | M18: Paid | N18: Sarah 2 Mar 2026: 'I'll send the final invoice on to my sister Catherine to pay.' Brad 5 Mar 2026: 'Also just confirming the invoice has come through, much appreciated.' | PDF '50 Dale St - Final Payment - Invoice.pdf' NOT opened. Amount DERIVED as the stated remaining 30% of the $5,800 + GST quote = $2,001 incl. This may be UNDERSTATED - new rear corner boards were supplied/replaced and painted, which was extra to the original scope, and may have been added to this invoice. NEEDS THE PDF CHECKED. Payment date is the date Brad acknowledged receipt, not necessarily the bank value date. | O18: 19cbbff0ebfcf78f
A19: 2026-03-04 | B19: — | C19: Danya Meakins | E19: 56 Dale Street - ceiling repaint, final balance | F19: Final | G19: 1024 | H19: 153.6 | I19: 1177.6 | J19: Yes | K19: PDF read | M19: Unknown | N19: No reply in the thread and no payment reference elsewhere in the mailbox. | PDF '56 Dale St - Final Payment - Invoice.pdf' NOT opened; no figures in body. Job total $1,280 + GST = $1,472 incl, but the balance cannot be derived because the deposit amount is unknown. NEEDS THE PDF CHECKED and payment status confirmed against the bank. | O19: 19cb73923ba5ad63
A20: 2026-03-04 | B20: — | C20: Cam | D20: Latch Build Ltd (cam@latchbuild.co.nz / hello@latchbuild.co.nz) | E20: 1 Ivy Lane - bathroom repair paint works (prime/paint wall repairs; fill, prime, paint replacement timber frames and skirtings) | F20: Other | G20: 426 | H20: 63.9 | I20: 489.9 | J20: No | K20: Owner's ledger (Business Data workbook) - invoice PDF unreadable | M20: Unknown | N20: Latch Build 4 Mar 2026: 'Got the invoice thanks. Will get it sorted.' Latch Build 15 Mar 2026: 'Invoice is in the system - it didn't have a due date on it so I set it to default which is 20th of the month following - although I've pulled it back to this month in your case.' No actual payment confirmation found. | PDF 'invoice for Latch - Invoice.pdf' NOT opened; no figures in body and no quote for this job anywhere in the mailbox. B2B customer. Likely paid late March 2026 but unconfirmed - CHECK THE BANK. Also note the invoice was issued with NO DUE DATE on it. | O20: 19cb742417c6d31b
A21: 2026-03-14 | B21: — | C21: Glenda Turner | E21: 29 Tomtit Crescent, Lake Hawea - retaining wall, final balance | F21: Final | G21: 806 | H21: 120.9 | I21: 926.9 | J21: No | K21: email body | L21: 2026-03-17 | M21: Paid | N21: Brad emailed 'Receipt for Payment' with receipt PDF attached on 17 Mar 2026 (thread 19cfd7ed65a0e342); Glenda replied 'Thanks!'. | Variation UP: wall was larger than quoted (a section continued behind the gate), requiring an extra 4L of Resene Lumbersider. Extra paint cost of $120 added to the invoice; additional labour for that section was NOT charged (absorbed by Lakeside). | PDF 'final invoice for Glenda - Retaining Wall - Invoice.pdf' NOT opened. Amount DERIVED: $980 quote + $120 extra paint = $1,100 + GST = $1,265 incl, less deposit $338.10 = $926.90 incl. It is NOT stated whether the $12 | O21: 19ceab168dca2286
A22: 2026-03-17 | B22: — | C22: Wes (and Ailsa) | E22: Bathroom wallpapering | F22: Final | G22: 1119.13 | H22: 167.87 | I22: 1287 | J22: Yes | K22: PDF read | M22: Unknown | N22: No reply in the thread and no payment reference elsewhere in the mailbox. | PDF 'Wes Bathroom - Invoice - Invoice.pdf' NOT opened; no figures in body and no quote for this job in the mailbox. Property address not stated. NEEDS THE PDF CHECKED and payment status confirmed against the bank. | O22: 19cfa408694ba76d
A23: 2026-03-24 | B23: INV-J12 | C23: Toni Fox (Assistant Property Manager) | D23: Home & Co. Property Management Ltd | E23: 3 Merivale Avenue - exterior cedar cladding prep and re-stain | F23: Deposit | G23: 2175 | H23: 326.25 | I23: 2501.25 | J23: No | K23: email body | M23: Unknown | N23: Toni Fox 24 Mar 2026: 'Thank you, I will process that now. We normally pay out on the 1st and 15th of each month if that is ok.' No confirmation of actual payment found. | Invoice no. taken from attachment filename 'INV-J12.pdf'. Body gives NO amount and NO percentage. Amount DERIVED ASSUMING a 30% deposit (Lakeside's usual rate) on the accepted quote of $7,250 + GST = $8,337.50 incl: 30% = $2,501.25 incl. THE PERCENTAGE IS AN ASSUMPTION - NEEDS THE PDF CHECKED. Billed to the property manager, processed through the property account. Likely paid ~1 April 2026 - CHECK THE BANK. | O23: 19d1e56df8eb3493
A24: 2026-04-05 | B24: INV-027 (attachment INV-027-J13-Deposit.pdf) | C24: Toni Fox (Assistant Property Manager) | D24: Home & Co. Property Management Ltd | E24: 10 McLeod Avenue - cedar restain and garage door painting | F24: Deposit | G24: 1845 | H24: 276.75 | I24: 2121.75 | J24: Yes | K24: PDF read | M24: Unknown | N24: No payment confirmation found. Work did not start until 11 May 2026; final invoice for this job was issued 20 May 2026 (outside this period). | Body states it is a 30% deposit but gives NO dollar amount, and the underlying quote for 10 McLeod Avenue does not appear in the mailbox, so no derivation is possible. NEEDS THE PDF CHECKED. Note the invoice number 'INV-027' does not follow the 'INV-J..' pattern used on the other Home & Co invoices. | O24: 19d5efa8fce440b0
A25: 2026-04-08 | B25: — | C25: Leigh Cashen | D25: Riverstone (leigh@riverstone.net.nz) | E25: 9 Hikuwai Drive - wallpaper installation to toilet wall (5 drops, pattern matched) | F25: Final | G25: 490 | H25: 73.5 | I25: 563.5 | J25: No | K25: email body | M25: Unknown | N25: No reply in the thread and no payment reference elsewhere in the mailbox. | Attachment is 'invoice for Leigh.XLSX' (a spreadsheet, not the usual PDF) and was NOT opened. Amount DERIVED from the accepted quote in the same thread: $490 + GST = $563.50 incl. NEEDS THE FILE CHECKED and payment status confirmed against the bank. | O25: 19d651691ff2a559
A26: 2026-04-12 | B26: INV-Q032-deposit | C26: Rebecca Maplesden | E26: 32 Malvern Road - cedar staining (prep, wash, mask, stain, scaffold, materials) | F26: Deposit | G26: 900 | H26: 135 | I26: 1035 | J26: Yes | K26: email body | M26: Paid | N26: Rebecca 16 Apr 2026: 'I'll pay deposit in next couple of days.' Rebecca 2 May 2026: 'I payed the deposit a couple of weeks ago.' Brad 6 May 2026: 'You've already paid the $1,035 incl. GST deposit.' | The job was later repriced DOWN on completion: final invoice INV-Q032-final (6 May 2026, OUTSIDE this period) reduced the job total from $3,450 incl GST to $2,528.85 incl GST, leaving a balance of $1,493.85 incl GST. The deposit was not changed. | The $1,035 incl GST figure is stated explicitly, but in a LATER email (6 May 2026), not in the 12 April invoice email - the April email body gives no fi | O26: 19d7618efffdedbe
A27: 2026-04-22 | B27: INV-J12-F | C27: Toni Fox (Assistant Property Manager) | D27: Home & Co. Property Management Ltd | E27: 3 Merivale Avenue - cedar restain completed (north side stripped to bare + Resene Woodsman oil; front/rear/sheltered Resene Waterborne Woodsman) | F27: Final | G27: 7075 | H27: 1061.25 | I27: 8136.25 | J27: No | K27: email body | M27: Unknown | N27: Toni Fox 23 Apr 2026: 'Thank you so much for this much appreciated. The property looks good, the owner will be pleased.' No payment confirmation found by 30 April 2026. | Variation UP of $2,000 + GST ($2,300 incl) approved by the owner via Toni Fox on 7 April 2026 for additional prep (sanding sun-exposed elevations back to bare timber after the old film-forming coating was found to be delaminating and incompatible with the oil stain). Lakeside absorbed a portion of the extra labour. | Invoice no. from attachment filename 'INV-J12-F.pdf'. Amount DERIVED: quote $7,250 + approved variation $2,000 | O27: 19db3e886a6b5097
A28: 2026-04-25 | B28: INV-PHW | C28: Steven Jin | D28: UCL Commercial Ltd (uclnz.co.nz) | E28: Pizza Hut Wanaka - plastering and painting to a small wall and bulkhead (fit-out) | F28: Final | G28: 2559 | H28: 383.85 | I28: 2942.85 | J28: Yes | K28: email body | M28: Unknown | N28: No payment confirmation found. Later contact (16-17 June 2026) was about a Google review only, with no mention of payment. | Amounts STATED IN THE BODY: 'The total is $2,559 + GST, which comes to $2,942.85 incl. GST'. Invoice no. from attachment filename 'INV-PHW Pizza Hut Wanaka.pdf'. Commercial customer in Auckland; no PO/reference beyond 'pizza hut wanaka'. Payment status needs checking against the bank. | O28: 19d852a268e87ff4
A29: 2026-04-26 | B29: INV-AUB-deposit | C29: Richard Gray | E29: 84C Aubrey Road - exterior repaint and cedar maintenance | F29: Deposit | G29: 4470 | H29: 670.5 | I29: 5140.5 | J29: Yes | K29: email body | L29: 2026-04-27 | M29: Paid | N29: Richard Gray 28 Apr 2026 NZ (27 Apr UTC): 'Done'. | Amount STATED IN THE BODY: 'Deposit (30%): $5,140.50 incl GST'. Implies a job total of $17,135 incl GST ($14,900 + GST). Work was scheduled for a mid-May start, i.e. after period end. Customer's one-word 'Done' is the only payment evidence - worth confirming against the bank. | O29: 19dc72917d3f7e43
A30: 2026-04-26 | B30: INV-Q034-deposit | C30: Kevin Henderson | E30: 3 Parkview Street - full interior repaint | F30: Deposit | G30: 4398 | H30: 659.7 | I30: 5057.7 | J30: Yes | K30: email body | M30: Unknown | N30: No payment confirmation found. Follow-up emails on 5 May and 18 May discuss scheduling and then cancellation, without ever referring to the deposit having been paid or needing to be refunded. | JOB CANCELLED AFTER INVOICING. On 19 May 2026 (NZ) Kevin Henderson advised the house had been sold before work started. Brad replied 'No worries at all, these things happen and we completely understand.' NO credit note, refund or write-off is visible in the mailbox. | Amount STATED IN THE BODY: 'Deposit (30%): $5,057.70 incl GST'. Consistent with the quote of $14,660 + GST = $16,859 incl. ACCOUNTANT ACT | O30: 19dc7290ac5bfc2c
A31: 2026-04-28 | B31: INV-Q034-deposit | C31: Troy Nicholson | E31: 4 Perrow Street, Wanaka - interior ceiling repaint (per quote QUO-034), start scheduled 13 July 2026 | F31: Deposit | G31: 1035 | H31: 155.25 | I31: 1190.25 | J31: No | K31: email body | L31: 2026-04-29 | M31: Paid | N31: Troy Nicholson 29 Apr 2026: 'Thanks Bradley, deposit paid mate.' Brad 1 May 2026: 'Awesome Troy, thanks for that.' | Body gives NO amount and NO percentage. Amount DERIVED ASSUMING 30% of quote QUO-034 (Interior Ceiling Repaint) = $3,450 + GST = $3,967.50 incl; 30% = $1,190.25 incl. THE PERCENTAGE IS AN ASSUMPTION - NEEDS THE PDF CHECKED. WARNING: the attachment filename 'INV-Q034-deposit.pdf' is IDENTICAL to the file sent to Kevin Henderson two days earlier (26 Apr) - see adjustments for the reference clash. Income is deferred: work not scheduled until July 2026. The second quote QUO-035 (wal | O31: 19dcb79d6ce2682b
A32: 2026-05-06 | B32: INV-Q032-final | C32: Rebecca Maplesden | E32: 32 Malvern Rd, Wanaka - cedar staining / one-coat Dryden WoodOil maintenance coat (incl. cedar prep, chemical clean, scaffold hire, stain and materials) | F32: Final | G32: 1299 | H32: 194.85 | I32: 1493.85 | J32: Yes | K32: email body | L32: 2026-05-08 | M32: Paid | N32: Customer email 8 May 2026 (NZ): 'The full invoice has been paid and happy to provide a reference.' | Not a credit note, but the job was re-priced before final invoicing: original quote $3,450.00 incl GST reduced to $2,528.85 incl GST after switching to a one-coat Dryden WoodOil approach. Deposit of $1,035.00 incl GST had already been paid (deposit invoice pre-dates this period), leaving this $1,493.85 balance. | Brad's email states verbatim: 'The updated total comes to $2,528.85 incl. GST, reduced from the original $3,450 incl. GST quote. You've already paid the $1,035 incl. GST deposit, so th | O32: 19dfaf012a5c2464
A33: 2026-05-06 | B33: INV-CC-001 | C33: Craig Chirnside | E33: 18 Hewson Cres - window frame staining | F33: Other | G33: 420 | H33: 63 | I33: 483 | J33: Yes | K33: PDF read | M33: Unknown | N33: No reply and no payment confirmation anywhere in the mailbox. | Invoice number taken from the attachment filename 'INV-CC-001.pdf'. Email body is one line ('Please find attached invoice for the window frame work') with NO amount. Amount must be obtained from the PDF or the accounting system. Single-message thread, no customer response - payment status genuinely unknown. | O33: 19dfafe013d411e8
A34: 2026-05-21 | B34: INV-028-Final | C34: Toni Fox (Assistant Property Manager) | D34: Home & Co. Property Management Ltd | E34: 10 McLeod Ave - exterior cedar stain (Resene Woodsman Natural, Smokey Ash), incl. garage door and side elevations | F34: Final | J34: No | K34: email body | L34: 2026-06-15 | M34: Paid | N34: Toni Fox 21 May: 'I will send the photos to the owner and process the invoice'. 25 May Toni asked to pay in full on 15 June (owner's account short); Brad agreed: 'No worries.. the 15th works.' A Home & Co supplier remittance email was received 15 June 2026 (thread 19ec8e475826ee93, ID RBRE460060-RBAG000016). NOTE: the remittance detail is a PDF attachment that could not be read, so the allocation of that remittance to this invoice is INFERRED from the agreed date, not proven. | Invoice number from attachment filename 'INV-028-Final.pdf'. No amount anywhere in the email body - get it from the P | O34: 19e46d6cd2a5acb7
A35: 2026-05-26 | B35: INV-034-DEP | C35: Terry Emmitt (Secretary); Gordon Stewart (Treasurer) | D35: Central Lakes Equestrian Club Inc | E35: Administration Building, Cromwell Racecourse Reserve - repaint hallway/stairwell/access passageways (30% deposit) | F35: Deposit | G35: 1560 | H35: 234 | I35: 1794 | J35: Yes | K35: email body | M35: Unknown | N35: The Club's Treasurer ATTEMPTED payment on 26 May 2026 but it failed: Terry Emmitt 27 May (NZ): 'Last night our Treasurer tried to deposit $1,794 into the ANZ account outlined on the Invoice but the system said the account number is invalid.' Brad re-issued the invoice with correct BNZ details the same day. NO subsequent confirmation of successful payment appears in the mailbox. | RE-ISSUED 27 May 2026 (NZ) with corrected bank account details. Original showed an invalid ANZ account (old template); revised invoice shows Lakeside Painting Limited, BNZ 02-0312-0183213-000, reference INV-034-DEP. A | O35: 19d8a038ac00b2ae
A36: 2026-06-06 | B36: INV-034-FIN | C36: Terry Emmitt (Secretary); invoice passed to Gordon Stewart (Treasurer) | D36: Central Lakes Equestrian Club Inc | E36: Administration Building, Cromwell Racecourse Reserve - hallway, stairwell and access areas repaint (balance on completion) | F36: Final | G36: 3640 | H36: 546 | I36: 4186 | J36: Yes | K36: email body | M36: Unknown | N36: Terry Emmitt 8 June 2026: 'Have sent invoice to Gordon Stewart our Treasurer.' That is acknowledgement of receipt only - no payment confirmation anywhere in the mailbox. | Brad's email states: 'the final invoice (INV-034-FIN) for the balance of $4,186.00 (incl. GST) ... payable on receipt.' Deposit $1,794.00 + final $4,186.00 = $5,980.00 = the approved quote total, so the job reconciles. Customer raised two post-completion points (second-floor passage not painted - Brad confirmed it was outside QUO-034 scope; a missing smoke alarm unit - Brad denied responsibility). Neither resulted in a credi | O36: 19e9ab1a8f2f51be
A37: 2026-06-13 | B37: INV-B43C21 | C37: Toni Fox (Assistant Property Manager) | D37: Home & Co. Property Management Ltd | E37: 32 Ash Avenue - interior repaint (ceilings, walls, hallway, bathroom) - 30% deposit to secure booking | F37: Deposit | G37: 983.25 | H37: 147.49 | I37: 1130.74 | J37: Yes | K37: email body | M37: Unknown | N37: No reply in the thread. Home & Co supplier remittance emails were received on 1 July 2026 (thread 19f1ba20aed22181) and 14 July 2026 (thread 19f630d70ec5abbc) - one of these most likely covers this deposit, but the remittance detail is in an unreadable PDF attachment so this is NOT confirmed. | Brad's email states: 'the deposit invoice (INV-B43C21) for 32 Ash Avenue. It's $1,130.74 incl GST, the 30% deposit ... Balance of $2,638.39 incl GST will be invoiced on completion.' Implied job total $3,769.13 incl GST. GST/ex split derived at 15%. Single-message thread. | O37: 19ebeeeb440ee6b7
A38: 2026-06-15 | B38: INV-8836EB | C38: Jessica (Jess) Patrick (Property Manager) | D38: Home & Co. Property Management Ltd | E38: 7 Cairnmuir Street - interior painting / bathroom ceilings (deposit to secure booking) | F38: Deposit | G38: 596.85 | H38: 89.53 | I38: 686.38 | J38: Yes | K38: email body | L38: 2026-07-01 | M38: Paid | N38: Jess Patrick 16 June 2026: 'I will process that deposit today. It will be paid out to you on the 1st of July (We only do two pay outs a month)'. Confirmed retrospectively by Jess on 23 July: 'I have attached the first payment, and we paid $595 + Gst - $686.38'. A Home & Co supplier remittance email was received 1 July 2026 (thread 19f1ba20aed22181). | THIS IS THE INVOICE WITH THE GST ERROR. Brad, 23 July 2026: 'The deposit invoice had GST added twice, which pushed the balance out to $1,601.54.' The deposit invoice was NOT re-issued and the customer paid it as issued ($686.38). The error was co | O38: 19ec8451619105ae
A39: 2026-06-26 | B39: — | C39: Amy Bixby | D39: Amy Bixby Jewellery (invoice sent to personal address amy.bixby@gmail.com) | E39: Not stated in the email - job squeezed in during w/c 22 June 2026 | F39: Final | G39: 1150 | H39: 172.5 | I39: 1322.5 | J39: Yes | K39: PDF read | L39: 2026-06-26 | M39: Paid | N39: Customer reply same day, 26 June 2026: 'Thanks guys, paid and reviewed. Thanks again for an awesome job and for squeezing us in this week.' | Attachment filename is 'Invoice - Amy Bixby.pdf' - no invoice number and no amount anywhere in the email text. Amount and invoice number must come from the PDF or the accounting system. Payment is confirmed; only the value is missing. | O39: 19f01fe9fefc9033
A40: 2026-07-03 | B40: — | C40: Toni Fox (Assistant Property Manager) | D40: Home & Co. Property Management Ltd | E40: 32 Ash Avenue - interior repaint, final invoice on completion (living room ceiling, bedroom ceiling, ensuite ceiling, bathroom wall, hallway) | F40: Final | G40: 2294.25 | H40: 344.14 | I40: 2638.39 | J40: No | K40: email body | M40: Unknown | N40: No payment confirmation in the thread (Toni only discusses photos for the owner). Home & Co supplier remittance emails were received 14 July 2026 and 3 August 2026 - one may cover this, but the remittance PDFs could not be read. | DERIVED AMOUNT: the final-invoice email itself states no figure ('Final invoice attached for 32 Ash Ave'), attachment 'Invoice-32-ash-ave.pdf' with no invoice number. The $2,638.39 incl GST is the balance Brad explicitly quoted in the 13 June deposit email for this same job ('Balance of $2,638.39 incl GST will be invoiced on completion'). Verify against the PDF befor | O40: 19f24f2851823b6d
A41: 2026-07-17 | B41: INV-J20-F | C41: Troy Nicholson | E41: 4 Perrow Street, Wanaka - interior ceiling repaint (final / remaining balance) | F41: Final | G41: 2415 | H41: 362.25 | I41: 2777.25 | J41: Yes | K41: PDF read | M41: Unknown | N41: Single-message thread, no reply and no payment confirmation in the mailbox. | Invoice number from attachment filename 'Invoice-interior-ceiling-repaint-4-perrow-street-INV-J20-F.pdf'. Email says only 'the invoice for the remaining balance' with no figure. Context: quote QUO-034 for this job was $3,450 + GST = $3,967.50 incl GST, and a deposit invoice INV-Q034-deposit was issued 28 April 2026 and paid 29 April 2026 ('deposit paid mate'). The deposit AMOUNT was never stated in any email. IF the deposit followed Lakeside's usual 30% (not stated for this job), the balance would be about $2,777.25 | O41: 19f6de9138ab92f0
A42: 2026-07-23 | B42: INV-Q040 | C42: Jessica (Jess) Patrick (Property Manager) | D42: Home & Co. Property Management Ltd | E42: 7 Cairnmuir Street - bathroom ceilings repaint, job complete (final / balance owing) | F42: Final | G42: 1133.15 | H42: 169.97 | I42: 1303.12 | J42: Yes | K42: email body | M42: Unknown | N42: Jess Patrick 23 July 2026: 'If you can please clear that up we will pay the invoice at the end of the month.' No payment confirmation in the thread. A Home & Co supplier remittance email was received 3 August 2026 (thread 19fc56821a04e21d) which may cover it - PDF unreadable, so unconfirmed. Treat as UNPAID at 31 July 2026 unless the bank statement shows otherwise. | RE-ISSUED / CORRECTED - THIS IS THE KNOWN GST DOUBLE-CHARGE. INV-Q040 was first emailed 23 July 2026 12:52pm NZ showing a balance of $1,601.54 incl GST. The customer queried it. Brad replied the same day: 'The deposit invoice had | O42: 19f8c6bb570ac75a
F44: TOTAL | G44: =SUM(G6:G42) -> 58913.37 | H44: =SUM(H6:H42) -> 8837.01 | I44: =SUM(I6:I42) -> 67750.38
F45: Of which verified | I45: =SUMIF($J$6:$J$42,"Yes",$I$6:$I$42) -> 36849.34
F46: Unverified / derived | I46: =SUMIF($J$6:$J$42,"No",$I$6:$I$42) -> 30901.04
F47: Paid | I47: =SUMIF($M$6:$M$42,"Paid",$I$6:$I$42) -> 26078.08
F48: Not confirmed paid | I48: =$I$44-$I$47 -> 41672.3

Sheet Supplier Bills
A1: Supplier Bills & Receipts
A2: Lakeside Painting Limited · 19 Jan – 31 Jul 2026 · all amounts NZD · negative = credit note / refund
A5: Bill date | B5: Supplier | C5: Invoice no. | D5: Description / PO | E5: Category | F5: Amount ex GST | G5: GST | H5: Total incl GST | I5: Amount verified? | J5: Credit note? | K5: Payment date | L5: Payment status | M5: How paid / evidence | N5: Notes | O5: Gmail thread
A6: 2026-01-21 | B6: Trademax NZ Limited | C6: 2905 | D6: Easy Access all-in-one telescopic ladder 1.5m/5ft | E6: Equipment | F6: 555 | G6: 83.25 | H6: 638.25 | I6: Yes | K6: 2026-02-14 | L6: Paid | M6: Stripe receipt #1371-7836 from Trademax's merchant entity 'LR, GM, M & C McLean Partnership' (sales@trademax.co.nz), NZ$1,201.86 paid 14 Feb 2026, summary: 'Statement payment for invoice(s): WANAKA - 2905, WANAKA - 3013, WANAKA - 3023, WANAKA - 3118, WANAKA - 3119'. Matches the 31 Jan 2026 statement balance exactly. Stripe thread 19c58dfb84830e10. | N6: Lightspeed receipt #2905 = Xero invoice 'WANAKA - 2905' ($638.25, due 20 Feb 2026). One purchase, two emails. | O6: 19bdd4acf284f767
A7: 2026-01-21 | B7: AA Insurance Limited | C7: ASP036773136 | D7: AA Small Business Insurance annual policy. Cover: (1) Commercial Vehicles - Vehicle 1 rego RPL199, 2010 Mazda E1800 Van SWB, Third Party Only, use 'Tools Carrying', third party liability limit $20,000,000, standard excess $500; (2) Public and Product | E7: Insurance | F7: 724.02 | G7: 108.6 | H7: 832.62 | I7: Yes | K7: First instalment 2026-01-21, then 21st of each month | L7: Partially Paid Then Defaulted. 21 Feb 2026 Instalment Declined For Insufficient Funds (Aa Letter 25 Feb 2026). Aa Re-Attempted And Failed Again; Final Payment Reminder 11 Mar 2026 Stated The Policy Would Automatically Cancel Without Further Notice If The Outstanding Premium Was Not Received By The Next Monthly Debit Date (21 Mar 2026). No Further Correspondence On This Policy Number Exists In The Mailbox After 11 Mar 2026. | M7: DIRECT DEBIT ON A PERSONAL VISA CARD. Policy letter page 2: Account name 'BRADLEY HAMILTON', card type VISA CARD, card number 459694******7490, authorised by BRADLEY HAMILTON, instalment $69.38 on the 21st of every month. A Direct Debit Service Agreement PDF was attached to the 21 Jan 2026 email. The card is in Bradley Hamilton's personal name, NOT the company's - this is a personally-funded payme | N7: CRITICAL FOR THE ACCOUNTANT: the named insured on this policy is 'Rank Higher Limited' and 'Bradley Hamilton', with trading name 'Lakeside Painting'. It is NOT in the name of Lakeside Painting Limited. The premium was also paid from a personal VISA card. Both points affect whether Lakeside Painting Limited can claim this cost. Attachments read: Policy Letter, Policy Schedule, Direct Debit Service | O7: 19bde424a52be33b
A8: 2026-01-23 | B8: Dulux | C8: 0907154714 | D8: stock | E8: Materials & paint | F8: 188.57 | G8: 28.28 | H8: 216.85 | I8: Yes | K8: 2026-02-14 | L8: Paid | M8: Feb 2026 Dulux statement (thread 19ca71224bb8d58a) shows payment 14/02/2026 EFT 146009 $216.85, clearing the Jan 2026 closing balance of $216.85 (this invoice only). | N8: Corroborated by Dulux monthly statement for account 146009. GST split derived at 15% (total x 3/23); only the GST-inclusive total was stated in the email. | O8: 19bec2c4d936e09a
A9: 2026-01-23 | B9: Trademax NZ Limited | C9: 3013 | D9: LED rechargeable worklight, 2ft folding platform, 3-step double-sided ladder 0.9m, tape measure | E9: Equipment | F9: 369.46 | G9: 55.42 | H9: 424.88 | I9: Yes | K9: 2026-02-14 | L9: Paid | M9: Stripe receipt #1371-7836 from Trademax's merchant entity 'LR, GM, M & C McLean Partnership' (sales@trademax.co.nz), NZ$1,201.86 paid 14 Feb 2026, summary: 'Statement payment for invoice(s): WANAKA - 2905, WANAKA - 3013, WANAKA - 3023, WANAKA - 3118, WANAKA - 3119'. Matches the 31 Jan 2026 statement balance exactly. Stripe thread 19c58dfb84830e10. | N9: Includes a $2.25 discount on the folding platform (total savings line). The 3-step ladder on this receipt was later returned - see credit note 3909 of 20 Feb 2026. Lightspeed #3013 = Xero 'WANAKA - 3013'. | O9: 19be833429bb37c2
A10: 2026-01-26 | B10: Trademax NZ Limited | C10: 3023 | D10: 2 x white 10L bucket pails with lids | E10: Consumables | F10: 19.48 | G10: 2.92 | H10: 22.4 | I10: Yes | K10: 2026-02-14 | L10: Paid | M10: Stripe receipt #1371-7836 from Trademax's merchant entity 'LR, GM, M & C McLean Partnership' (sales@trademax.co.nz), NZ$1,201.86 paid 14 Feb 2026, summary: 'Statement payment for invoice(s): WANAKA - 2905, WANAKA - 3013, WANAKA - 3023, WANAKA - 3118, WANAKA - 3119'. Matches the 31 Jan 2026 statement balance exactly. Stripe thread 19c58dfb84830e10. | N10: Lightspeed #3023 = Xero 'WANAKA - 3023'. | O10: 19bf68ddcc4eece2
A11: 2026-01-28 | B11: Trademax NZ Limited | C11: 3118 | D11: 2 x Pelican hand-held pails, microfibre roller sleeves 9mm & 6mm 10pk, nook frame, pail liners 3pk | E11: Consumables | F11: 96.25 | G11: 14.44 | H11: 110.69 | I11: Yes | K11: 2026-02-14 | L11: Paid | M11: Stripe receipt #1371-7836 from Trademax's merchant entity 'LR, GM, M & C McLean Partnership' (sales@trademax.co.nz), NZ$1,201.86 paid 14 Feb 2026, summary: 'Statement payment for invoice(s): WANAKA - 2905, WANAKA - 3013, WANAKA - 3023, WANAKA - 3118, WANAKA - 3119'. Matches the 31 Jan 2026 statement balance exactly. Stripe thread 19c58dfb84830e10. | N11: Lightspeed #3118 = Xero 'WANAKA - 3118'. | O11: 19c00e8c2ccb205b
A12: 2026-01-28 | B12: Trademax NZ Limited | C12: 3119 | D12: Nook frame - soft grip 26cm threaded | E12: Consumables | F12: 4.9 | G12: 0.74 | H12: 5.64 | I12: Yes | K12: 2026-02-14 | L12: Paid | M12: Stripe receipt #1371-7836 from Trademax's merchant entity 'LR, GM, M & C McLean Partnership' (sales@trademax.co.nz), NZ$1,201.86 paid 14 Feb 2026, summary: 'Statement payment for invoice(s): WANAKA - 2905, WANAKA - 3013, WANAKA - 3023, WANAKA - 3118, WANAKA - 3119'. Matches the 31 Jan 2026 statement balance exactly. Stripe thread 19c58dfb84830e10. | N12: Separate 3-minute-later transaction from #3118, same item repeated. Lightspeed #3119 = Xero 'WANAKA - 3119'. | O12: 19c00eeb55e85fc9
A13: 2026-02-03 | B13: Dulux | C13: 0907315824 | D13: Pennys House | E13: Materials & paint | F13: 511.43 | G13: 76.71 | H13: 588.14 | I13: Yes | K13: 2026-03-18 | L13: Paid | M13: Mar 2026 Dulux statement (thread 19d47cad7b094bc9) shows payment 18/03/2026 EFT 146009 $1,076.85, clearing the Feb 2026 closing balance of $1,076.85 (all 8 Feb invoices). | N13: Corroborated by Dulux monthly statement for account 146009. GST split derived at 15% (total x 3/23); only the GST-inclusive total was stated in the email. | O13: 19c243931f9ce817
A14: 2026-02-03 | B14: Trademax NZ Limited | C14: 3333 | D14: Gib Roc tape 75m, GIB Plus 4 compound 4L bucket | E14: Materials & paint | F14: 47.48 | G14: 7.12 | H14: 54.6 | I14: Yes | L14: Paid | M14: No payment receipt in the mailbox. Inferred settled during March 2026: the 28 Feb 2026 statement shows $238.17 outstanding (3333 + 3397 + 3910 less credit 3909) and the 31 Mar 2026 statement shows only $219.34, i.e. the two March invoices, so the February balance had cleared. Exact payment date unknown. | N14: Lightspeed #3333 = Xero 'WANAKA - 3333' ($54.60, due 20 Mar 2026). | O14: 19c20b37223ef6b6
A15: 2026-02-04 | B15: Trademax NZ Limited | C15: 3397 | D15: Super-Tex carpet protection 500mm x 75m | E15: Consumables | F15: 41.3 | G15: 6.2 | H15: 47.5 | I15: Yes | L15: Paid | M15: No payment receipt in the mailbox. Inferred settled during March 2026: the 28 Feb 2026 statement shows $238.17 outstanding (3333 + 3397 + 3910 less credit 3909) and the 31 Mar 2026 statement shows only $219.34, i.e. the two March invoices, so the February balance had cleared. Exact payment date unknown. | N15: Lightspeed #3397 = Xero 'WANAKA - 3397' ($47.50, due 20 Mar 2026). | O15: 19c266eb2c61020f
A16: 2026-02-11 | B16: Dulux | C16: 0907460733 | D16: 1 Perrow Street | E16: Materials & paint | F16: 88.02 | G16: 13.2 | H16: 101.22 | I16: Yes | K16: 2026-03-18 | L16: Paid | M16: Mar 2026 Dulux statement shows payment 18/03/2026 EFT $1,076.85 clearing the Feb 2026 balance (all 8 Feb invoices). | N16: Corroborated by Dulux monthly statement for account 146009. Emailed together with 0907464202. GST split derived at 15% (total x 3/23); only the GST-inclusive total was stated in the email. | O16: 19c4d68c42370b70
A17: 2026-02-11 | B17: Dulux | C17: 0907464202 | D17: 1 Perrow street | E17: Materials & paint | F17: 33.24 | G17: 4.99 | H17: 38.23 | I17: Yes | K17: 2026-03-18 | L17: Paid | M17: Mar 2026 Dulux statement shows payment 18/03/2026 EFT $1,076.85 clearing the Feb 2026 balance (all 8 Feb invoices). | N17: Corroborated by Dulux monthly statement for account 146009. Emailed together with 0907460733. GST split derived at 15% (total x 3/23); only the GST-inclusive total was stated in the email. | O17: 19c4d68c42370b70
A18: 2026-02-20 | B18: Trademax NZ Limited | C18: 3909 | D18: RETURN: 1 x Easy Access 3-step double-sided ladder 0.9m (OXDS03) | E18: Equipment | F18: -150 | G18: -22.5 | H18: -172.5 | I18: Yes | J18: Yes | L18: Paid | M18: No payment receipt in the mailbox. Inferred settled during March 2026: the 28 Feb 2026 statement shows $238.17 outstanding (3333 + 3397 + 3910 less credit 3909) and the 31 Mar 2026 statement shows only $219.34, i.e. the two March invoices, so the February balance had cleared. Exact payment date unknown. | N18: CREDIT NOTE. Lightspeed receipt #3909 shows qty -1, subtotal -$150.00, GST -$22.50, TOTAL -$172.50. Returns the 3-step ladder bought on #3013 (23 Jan 2026). The Xero email is worded 'Here's invoice WANAKA - 3909 for NZD 172.50' but its attachment is named 'Credit Note WANAKA - 3909.pdf', and the 28 Feb 2026 statement arithmetic confirms it is a credit: 54.60 + 47.50 + 308.57 - 172.50 = 238.17. Rec | O18: 19c78063e176eb29
A19: 2026-02-20 | B19: Trademax NZ Limited | C19: 3910 | D19: Easy Access 4-step double-sided ladder 1.2m, 2 x delicate purple tape, microfibre roller sleeves 6mm & 9mm 10pk, masking tape 300mm | E19: Equipment | F19: 268.32 | G19: 40.25 | H19: 308.57 | I19: Yes | L19: Paid | M19: No payment receipt in the mailbox. Inferred settled during March 2026: the 28 Feb 2026 statement shows $238.17 outstanding (3333 + 3397 + 3910 less credit 3909) and the 31 Mar 2026 statement shows only $219.34, i.e. the two March invoices, so the February balance had cleared. Exact payment date unknown. | N19: Bought 17 minutes after the ladder return #3909 - the 3-step ladder was swapped for this 4-step. Mixed receipt: ladder $190.00 (equipment) plus $78.32 of tapes and roller sleeves (consumables). Lightspeed #3910 = Xero 'WANAKA - 3910'. | O19: 19c7815b3fe3fc71
A20: 2026-02-24 | B20: Dulux | C20: 0907698868 | D20: 50 Dale | E20: Materials & paint | F20: 23.13 | G20: 3.47 | H20: 26.6 | I20: Yes | K20: 2026-03-18 | L20: Paid | M20: Mar 2026 Dulux statement shows payment 18/03/2026 EFT $1,076.85 clearing the Feb 2026 balance (all 8 Feb invoices). | N20: Corroborated by Dulux monthly statement for account 146009. GST split derived at 15% (total x 3/23); only the GST-inclusive total was stated in the email. | O20: 19c9059ff3ee0bca
A21: 2026-02-26 | B21: Dulux | C21: 0907747267 | D21: TROY | E21: Materials & paint | F21: 85.04 | G21: 12.76 | H21: 97.8 | I21: Yes | K21: 2026-03-18 | L21: Paid | M21: Mar 2026 Dulux statement shows payment 18/03/2026 EFT $1,076.85 clearing the Feb 2026 balance (all 8 Feb invoices). | N21: Corroborated by Dulux monthly statement for account 146009. One of 4 invoices in a single email; PO/location taken from the Feb statement. GST split derived at 15% (total x 3/23); only the GST-inclusive total was stated in the email. | O21: 19c9aa49b8e25f94
A22: 2026-02-26 | B22: Dulux | C22: 0907747564 | D22: STOCK | E22: Materials & paint | F22: 15.69 | G22: 2.35 | H22: 18.04 | I22: Yes | K22: 2026-03-18 | L22: Paid | M22: Mar 2026 Dulux statement shows payment 18/03/2026 EFT $1,076.85 clearing the Feb 2026 balance (all 8 Feb invoices). | N22: Corroborated by Dulux monthly statement for account 146009. One of 4 invoices in a single email; PO/location taken from the Feb statement. GST split derived at 15% (total x 3/23); only the GST-inclusive total was stated in the email. | O22: 19c9aa49b8e25f94
A23: 2026-02-26 | B23: Dulux | C23: 0907747629 | D23: DANYA | E23: Materials & paint | F23: 167.89 | G23: 25.18 | H23: 193.07 | I23: Yes | K23: 2026-03-18 | L23: Paid | M23: Mar 2026 Dulux statement shows payment 18/03/2026 EFT $1,076.85 clearing the Feb 2026 balance (all 8 Feb invoices). | N23: Corroborated by Dulux monthly statement for account 146009. One of 4 invoices in a single email; PO/location taken from the Feb statement. GST split derived at 15% (total x 3/23); only the GST-inclusive total was stated in the email. | O23: 19c9aa49b8e25f94
A24: 2026-02-26 | B24: Dulux | C24: 0907747634 | D24: STOCK | E24: Materials & paint | F24: 11.96 | G24: 1.79 | H24: 13.75 | I24: Yes | K24: 2026-03-18 | L24: Paid | M24: Mar 2026 Dulux statement shows payment 18/03/2026 EFT $1,076.85 clearing the Feb 2026 balance (all 8 Feb invoices). | N24: Corroborated by Dulux monthly statement for account 146009. One of 4 invoices in a single email; PO/location taken from the Feb statement. GST split derived at 15% (total x 3/23); only the GST-inclusive total was stated in the email. | O24: 19c9aa49b8e25f94
A25: 2026-02-27 | B25: Tool Junction Ltd | C25: 25118 (order #5126) | D25: FESTOOL DTSC400 Delta Sander Hybrid Set (578141) x1. Freight free. | E25: Equipment | F25: 1522 | G25: 228.3 | H25: 1750.3 | I25: Yes | K25: 2026-02-27 | L25: Paid | M25: Shopify order confirmation states: 'Payment / Visa / ending with 5996'. CARD ENDING 5996 — the accountant should confirm whether this is the company card or Bradley's personal card; the same card (5996) was used for the Hireworx hire payment. | N25: Order confirmation (thread 19c9da6ad21a7f81, 2026-02-27) carries the full price breakdown. Tax invoice #25118 was emailed separately on 2026-03-01 as a PDF (thread 19cab1da66a60e77) — invoice date on the PDF may read 2 March 2026. Largest single capital purchase found in the period. | O25: 19c9da6ad21a7f81
A26: 2026-02-27 | B26: Taskhound (Taskhound Limited), 10 Dow Close, Wanaka | C26: INV-0020 | D26: Maintenance/handyman work. Lines: Vehicle and Technician 1.00 @ $40.00 = $40.00; Replacement of 4x exterior corner moulding 1.00 @ $80.00 = $80.00; Job Materials and Consumables (screws, sealants, fittings and other items used in service delivery) 1. | E26: Subcontractor | F26: 340 | G26: 51 | H26: 391 | I26: Yes | L26: Unknown - Invoice Due 6 Mar 2026. No Remittance, Receipt Or Payment Confirmation For This Invoice Exists Anywhere In The Mailbox. | M26: Invoice requests bank deposit to Taskhound Limited, Kiwibank 38-9027-0333199-00, using the invoice number as reference. No card or cash indicator. | N26: Delivered as a Xero-generated 'invoice is due' email with the PDF attached. Terms: payment within 7 days, 10% interest on overdue amounts. | O26: 19c9d7fead466921
A27: 2026-03-03 | B27: Trademax NZ Limited | C27: 4224 | D27: 2 x Pelican pail liners 3pk, Norton no-fil sandpaper roll 115mm 120g, dual-angle blue | E27: Consumables | F27: 34.55 | G27: 5.18 | H27: 39.73 | I27: Yes | K27: 2026-04-19 | L27: Paid | M27: Stripe receipt #1296-0588, NZ$219.34 paid 19 Apr 2026, summary: 'Statement payment for invoice(s): WANAKA - 4224, WANAKA - 4262'. Matches the 31 Mar 2026 statement balance exactly. Stripe thread 19da392f69375360. | N27: Lightspeed #4224 = Xero 'WANAKA - 4224'. | O27: 19cb0148257ade86
A28: 2026-03-03 | B28: Trademax NZ Limited | C28: 4262 | D28: Wire brush, 3 x Haydn pro edge scrapers (25/38/50mm), Pal contract filler 210ml, Haydn extension pole 1.6-3.2m, Arlec 20m extension lead, Ox 13mm small tool | E28: Equipment | F28: 156.18 | G28: 23.43 | H28: 179.61 | I28: Yes | K28: 2026-04-19 | L28: Paid | M28: Stripe receipt #1296-0588, NZ$219.34 paid 19 Apr 2026, summary: 'Statement payment for invoice(s): WANAKA - 4224, WANAKA - 4262'. Matches the 31 Mar 2026 statement balance exactly. Stripe thread 19da392f69375360. | N28: Mostly hand tools; includes $15.63 of filler (materials). Lightspeed #4262 = Xero 'WANAKA - 4262'. | O28: 19cb13ee49e917f7
A29: 2026-03-04 | B29: Dulux | C29: 0907837114 | D29: 56 SDALE STREET | E29: Materials & paint | F29: 33.76 | G29: 5.06 | H29: 38.82 | I29: Yes | K29: 2026-04-19 | L29: Paid | M29: Apr 2026 Dulux statement (thread 19de27ee894aee49) shows payment 19/04/2026 EFT 146009 $202.31, which equals the Mar 2026 balance of $1,655.88 LESS invoice 0908015736 ($1,453.57); i.e. it cleared the four smaller March invoices. | N29: Corroborated by Dulux monthly statement for account 146009. GST split derived at 15% (total x 3/23); only the GST-inclusive total was stated in the email. | O29: 19cb9980245c0de7
A30: 2026-03-04 | B30: R&S Trade Centre Ltd | C30: 55377 | D30: Festool Granat Delta sanding discs (120g x26, 80g x26, 150g x25) + flat rate shipping | E30: Equipment | F30: 97.74 | G30: 14.67 | H30: 112.41 | I30: Yes | K30: 2026-03-04 | L30: Paid | M30: Order confirmation states 'Payment method: Payment Express' — paid online at time of order, not on account. | N30: Amounts read from the WooCommerce order confirmation body. The matching tax invoice PDF was emailed 2026-03-05 (thread 19cbc46c7417a3c2). Consumables, not capital. | O30: 19cb70cb1b334384
A31: 2026-03-13 | B31: Dulux | C31: 0908015736 | D31: 113 R3 | E31: Materials & paint | F31: 1263.97 | G31: 189.6 | H31: 1453.57 | I31: Yes | L31: Unknown | M31: Appears on the Mar 2026 statement but was NOT included in the 19/04/2026 payment of $202.31 (= March total less this invoice). It never reappears on any later statement and no month shows an Overdue balance, so it was removed from account 146009 (credited/reversed/transferred). No credit note email was found. | N31: ANOMALY: same amount and same PO ('113 R3') as invoice 0908369599 dated 02/04/2026 - likely a duplicate/re-issue pair. Verify with Dulux before booking. GST split derived at 15% (total x 3/23); only the GST-inclusive total was stated in the email. | O31: 19ce8214edf30017
A32: 2026-03-16 | B32: Dulux | C32: 0908038921 | D32: WES BATHROOM | E32: Materials & paint | F32: 84.14 | G32: 12.62 | H32: 96.76 | I32: Yes | K32: 2026-04-19 | L32: Paid | M32: Apr 2026 Dulux statement shows payment 19/04/2026 EFT $202.31 = March total less invoice 0908015736; covers this invoice. | N32: Corroborated by Dulux monthly statement for account 146009. One of 3 invoices in a single email; PO/location taken from the Mar statement. GST split derived at 15% (total x 3/23); only the GST-inclusive total was stated in the email. | O32: 19cf76043a4a9c56
A33: 2026-03-16 | B33: Dulux | C33: 0908040110 | D33: STOCK | E33: Materials & paint | F33: 30.28 | G33: 4.54 | H33: 34.82 | I33: Yes | K33: 2026-04-19 | L33: Paid | M33: Apr 2026 Dulux statement shows payment 19/04/2026 EFT $202.31 = March total less invoice 0908015736; covers this invoice. | N33: Corroborated by Dulux monthly statement for account 146009. One of 3 invoices in a single email; PO/location taken from the Mar statement. GST split derived at 15% (total x 3/23); only the GST-inclusive total was stated in the email. | O33: 19cf76043a4a9c56
A34: 2026-03-16 | B34: Dulux | C34: 0908051787 | D34: STOCK | E34: Materials & paint | F34: 27.75 | G34: 4.16 | H34: 31.91 | I34: Yes | K34: 2026-04-19 | L34: Paid | M34: Apr 2026 Dulux statement shows payment 19/04/2026 EFT $202.31 = March total less invoice 0908015736; covers this invoice. | N34: Corroborated by Dulux monthly statement for account 146009. One of 3 invoices in a single email; PO/location taken from the Mar statement. GST split derived at 15% (total x 3/23); only the GST-inclusive total was stated in the email. | O34: 19cf76043a4a9c56
A35: 2026-03-25 | B35: R&S Trade Centre Ltd | C35: 55570 | D35: Festool Granat Delta sanding discs (60g x50, 100g x30). Free shipping. | E35: Equipment | F35: 87 | G35: 13.05 | H35: 100.05 | I35: Yes | K35: 2026-03-25 | L35: Paid | M35: Order confirmation states 'Payment method: Payment Express' — paid online at time of order. | N35: Tax invoice PDF emailed 2026-03-26 (thread 19d286b55f77ba01). | O35: 19d23a54344a9a43
A36: 2026-03-30 | B36: Trademax NZ Limited | C36: 5173 | D36: 50 x Norton No-Fil SG 125mm 60G sanding discs | E36: Consumables | F36: 89.1 | G36: 13.37 | H36: 102.47 | I36: Yes | L36: Unknown | M36: No Xero invoice was ever issued for this receipt and it does not appear on the 31 Mar 2026 statement ($219.34 = invoices 4224 + 4262 only), because it was reversed in full 47 minutes later by refund #5175. Net charge to the account: nil. | N36: Reversed in full the same day by credit note #5175. Lightspeed only - no matching Xero invoice. Net effect on the account is zero; include only if the accountant wants the gross in/out shown. | O36: 19d3becddd00c80d
A37: 2026-03-30 | B37: Trademax NZ Limited | C37: 5175 | D37: REFUND: 50 x Norton No-Fil SG 125mm 60G sanding discs | E37: Consumables | F37: -89.1 | G37: -13.37 | H37: -102.47 | I37: Yes | J37: Yes | L37: Unknown | M37: No Xero credit note email; does not appear on the 31 Mar 2026 statement. Offsets receipt #5173 exactly. | N37: CREDIT NOTE / REFUND. Lightspeed receipt #5175 shows qty -50, subtotal -$89.10, GST -$13.37, TOTAL -$102.47, Note: 'refund'. Reverses #5173 issued 47 minutes earlier the same day. | O37: 19d3c178f29e021e
A38: 2026-03-31 | B38: Google New Zealand Limited | C38: 5530833582 | D38: Google Workspace Business Standard - new commitment, service period 8 Mar 2026 to 31 Mar 2026, 1 seat. Domain lakesidepainting.co.nz. Billing ID 5705-6557-7587. | E38: Software & subscriptions | F38: 12.19 | G38: 1.83 | H38: 14.02 | I38: Yes | K38: Auto-charged on/around 2026-04-01 | L38: Paid Automatically | M38: Automatic card charge - email states 'The balance will be automatically charged so you don't have to do anything'. The card used is not disclosed in the invoice or email. Billing contact on the invoice is 'Bradley Hamilton, Lakeside Painting, 35 old racecourse road, Albert Town 9305' (home address, personal name). | N38: Part month only - the free trial ended 8 March 2026. GST is charged by a NZ-registered entity (Google New Zealand Limited, GST 93-685-547) at 15%, so the GST is claimable as a normal NZ input credit. | O38: 19d499654471e4a3
A39: 2026-04-02 | B39: Dulux | C39: 0908369599 | D39: 113 R3 | E39: Materials & paint | F39: 1263.97 | G39: 189.6 | H39: 1453.57 | I39: Yes | L39: Unknown | M39: Does NOT appear on the Apr 2026 Dulux statement (which lists only $365.26 of April invoices) nor on any later statement, and no month shows an Overdue balance. No payment evidence and no credit note email found. | N39: ANOMALY: not on any monthly statement. Same amount ($1,453.57) and same PO ('113 R3') as invoice 0908015736 dated 13/03/2026 - likely a duplicate/re-issue pair. Verify with Dulux before booking. GST split derived at 15% (total x 3/23); only the GST-inclusive total was stated in the email. | O39: 19d4f235804b8283
A40: 2026-04-08 | B40: R&S Trade Centre Ltd | C40: 55664 | D40: Festool Granat Delta sanding discs (40g x20, 60g x60). Free shipping. | E40: Equipment | F40: 87.8 | G40: 13.17 | H40: 100.97 | I40: Yes | K40: 2026-04-08 | L40: Paid | M40: Order confirmation states 'Payment method: Payment Express' — paid online at time of order. | N40: Tax invoice PDF emailed 2026-04-08 (thread 19d6b5dd173ceb02). | O40: 19d696d8fee69e29
A41: 2026-04-15 | B41: Trademax NZ Limited | C41: 5653 | D41: Intex LED 60W corded worklight, Intex 2.5W LED headlamp, Straitflex medium tape 30m, Gib Trade Finish Multi 15L, 2 x Futureprotect masking film, Gib paper tape 75m, microfibre roller sleeves | E41: Equipment | F41: 413.49 | G41: 62.02 | H41: 475.51 | I41: Yes | K41: 2026-05-18 | L41: Paid | M41: Stripe receipt #1993-8510, NZ$475.51 paid 18 May 2026, summary: 'Payment for invoice(s) WANAKA - 5653'. Matches the 30 Apr 2026 statement balance exactly. Stripe thread 19e377b70171db52. | N41: Mixed receipt: $225.00 of lighting (equipment) and $188.49 of plaster/masking/roller stock (materials & consumables). Categorised on the largest component. Lightspeed #5653 = Xero 'WANAKA - 5653'. | O41: 19d8df6a95c6b6f0
A42: 2026-04-21 | B42: Dulux | C42: 0908671574 | D42: pizza hut | E42: Materials & paint | F42: 28.52 | G42: 4.28 | H42: 32.8 | I42: Yes | K42: 2026-05-18 | L42: Paid | M42: May 2026 Dulux statement (thread 19e8224018579849) shows payment 18/05/2026 EFT 146009 $365.26, clearing the Apr 2026 closing balance of $365.26 (all 3 April invoices). | N42: Corroborated by Dulux monthly statement for account 146009. GST split derived at 15% (total x 3/23); only the GST-inclusive total was stated in the email. | O42: 19db0ff1f7dc5517
A43: 2026-04-22 | B43: Dulux | C43: 0908695469 | D43: nicoles job | E43: Materials & paint | F43: 268.65 | G43: 40.3 | H43: 308.95 | I43: Yes | K43: 2026-05-18 | L43: Paid | M43: May 2026 Dulux statement shows payment 18/05/2026 EFT $365.26 clearing the Apr 2026 balance (all 3 April invoices). | N43: Corroborated by Dulux monthly statement for account 146009. GST split derived at 15% (total x 3/23); only the GST-inclusive total was stated in the email. | O43: 19db6248135734f0
A44: 2026-04-24 | B44: Dulux | C44: 0908727761 | D44: nicoles job | E44: Materials & paint | F44: 20.44 | G44: 3.07 | H44: 23.51 | I44: Yes | K44: 2026-05-18 | L44: Paid | M44: May 2026 Dulux statement shows payment 18/05/2026 EFT $365.26 clearing the Apr 2026 balance (all 3 April invoices). | N44: Corroborated by Dulux monthly statement for account 146009. GST split derived at 15% (total x 3/23); only the GST-inclusive total was stated in the email. | O44: 19dc0d7362367a76
A45: 2026-04-30 | B45: Google New Zealand Limited | C45: 5553913919 | D45: Google Workspace Business Standard - commitment, service period 1 Apr 2026 to 30 Apr 2026, 1 seat. Domain lakesidepainting.co.nz. | E45: Software & subscriptions | F45: 15.75 | G45: 2.36 | H45: 18.11 | I45: Yes | K45: Auto-charged on/around 2026-05-01 | L45: Paid Automatically | M45: Automatic card charge; card not disclosed. | N45: First full month at the standard rate: NZ$15.75 + GST = NZ$18.11. | O45: 19de3d7b1dc02d76
A46: 2026-05-04 | B46: Dulux | C46: 0908872288 | D46: 32 Melvin road | E46: Materials & paint | F46: 27.92 | G46: 4.19 | H46: 32.11 | I46: Yes | K46: 2026-06-20 | L46: Paid | M46: Jun 2026 Dulux statement (thread 19f1ca2b14297a40) shows payment 20/06/2026 EFT 146009 $1,449.01, clearing the May 2026 closing balance of $1,449.01 (all 11 May invoices). | N46: Corroborated by Dulux monthly statement for account 146009. GST split derived at 15% (total x 3/23); only the GST-inclusive total was stated in the email. | O46: 19df3f039d26f41d
A47: 2026-05-05 | B47: Trademax NZ Limited | C47: WAN6330 | D47: Dryden 10L clear base + Lite Oak+ tint 500ml, paint stirrer, microfibre roller sleeves 9mm & 6mm, PAL Legend 75mm oval brush, 3 x pail liners | E47: Materials & paint | F47: 511.3 | G47: 76.7 | H47: 588 | I47: Yes | K47: 2026-07-01 | L47: Paid | M47: Stripe receipt #1872-7279, NZ$588.00 paid 1 Jul 2026, summary: 'Statement payment for invoice(s): WANAKA - WAN6330'. This invoice was shown as the $588.00 overdue portion on the 30 Jun 2026 statement. Stripe thread 19f1ba7ab19f9123. | N47: Paid 11 days after the 20 Jun 2026 due date; shown as the $588.00 overdue figure on the 30 Jun 2026 statement. Lightspeed #WAN6330 = Xero 'WANAKA - WAN6330'. First receipt using the new WAN-prefixed numbering. | O47: 19df4f3a6dec98eb
A48: 2026-05-05 | B48: Hireworx New Zealand Limited (Hireworx Wanaka) | C48: 241515 | D48: Equipment hire, delivered to 32 Malvern Road, Wanaka. Hire period Tue 5 May 2026 12:00 PM to Tue 5 May 2026 4:31 PM. Lines: Scaffold Tower 4.5m, 1 x Half Day @ $78.26 ex = $78.26; Delivery/Collection Hireworx National 0.25 Transporter Hourly @ $240.0 | E48: Equipment Hire | F48: 147.89 | G48: 22.19 | H48: 170.08 | I48: Yes | K48: 2026-05-04 | L48: Paid In Full. Invoice Shows 'Amount Paid $170.08', 'Balance Due $0.00' And A Line Note '4/05/2026 - Card Payment Of $170.08'. | M48: CREDIT CARD (paid via the Pin Payments 'Pay Now' link). The invoice carries a 'National Credit Card Surcharge' of $2.83 ex GST, which confirms card payment. Payment terms on the invoice are shown as 'Cash account' (i.e. no trade credit account - pay on the day). Which card was used is not stated. | N48: IMPORTANT - do not use the $166.83 figure from the 4 May booking email. That was the pre-payment booking total. The final tax invoice dated 5 May 2026 is $170.08 incl GST (the $3.25 difference is the credit card surcharge of $2.83 plus its GST of $0.42). Use $170.08 / GST $22.19. | O48: 19dfeac129634889
A49: 2026-05-12 | B49: Dulux | C49: 0909019353 | D49: stock | E49: Materials & paint | F49: 95.34 | G49: 14.3 | H49: 109.64 | I49: Yes | K49: 2026-06-20 | L49: Paid | M49: Jun 2026 Dulux statement shows payment 20/06/2026 EFT $1,449.01 clearing the May 2026 balance (all 11 May invoices). | N49: Corroborated by Dulux monthly statement for account 146009. GST split derived at 15% (total x 3/23); only the GST-inclusive total was stated in the email. | O49: 19e1d241f48c65d2
A50: 2026-05-13 | B50: Resene | C50: 424640171 | D50: 10 MCCLOUD AVE | E50: Materials & paint | F50: 181.7 | G50: 27.26 | H50: 208.96 | I50: No | L50: Unknown | M50: No payment evidence found. Not included in the 20/07/2026 MyResene direct-debit run (that run covered only 424763500, 424769024 and 424771838). Due date 20/06/2026 per the invoice PDF. | N50: Amount, invoice date and PO were NOT stated in the email body - read from the attached PDF tax invoice ('Invoice 424640171 Account D69359.pdf'). PDF states Subtotal $181.70, GST $27.26, Total $208.96, due 20/06/26, shop 087 Wanaka ColorShop. amounts_confirmed=false because the figure was not in the email body. | O50: 19e206b52fa726ec
A51: 2026-05-13 | B51: Resene | C51: 424640175 | D51: STOCK | E51: Materials & paint | F51: 52 | G51: 7.8 | H51: 59.8 | I51: No | L51: Unknown | M51: No payment evidence found. Not included in the 20/07/2026 MyResene direct-debit run. Due date 20/06/2026 per the invoice PDF. | N51: Amount, invoice date and PO were NOT stated in the email body - read from the attached PDF tax invoice ('Invoice 424640175 Account D69359.pdf'). PDF states Subtotal $52.00, GST $7.80, Total $59.80, due 20/06/26. amounts_confirmed=false because the figure was not in the email body. | O51: 19e206b52c7bea70
A52: 2026-05-13 | B52: AA Insurance Limited | C52: ASP036836160 | D52: AA Small Business Insurance annual policy. Cover: (1) Commercial Vehicles - Vehicle 1 rego KAJ960, 2012 Nissan Caravan DX Van, Third Party Only, use 'Tools Carrying', third party liability limit $20,000,000, standard excess $500; (2) Public and Produ | E52: Insurance | F52: 738.52 | G52: 110.78 | H52: 849.3 | I52: Yes | K52: First instalment 2026-06-11, then 11th of each month | L52: Direct Debit Set Up; No Rejection Notices For This Policy Number Appear In The Mailbox, So Instalments Appear To Be Running. No Individual Payment Receipts Are Emailed By Aa. | M52: DIRECT DEBIT ON A VISA CARD IN THE COMPANY NAME. Policy letter page 2: Account name 'LAKESIDE PAINTING LTD', card type VISA CARD, card number 428455******5996, authorised by BRADLEY HAMILTON, instalment $70.77 on the 11th of every month. A Direct Debit Service Agreement PDF was attached. This is a DIFFERENT card from the one used on ASP036773136. | N52: Named insured is 'Lakeside Painting Limited' and 'Bradley Hamilton' - correct entity this time. An AA Member Discount was applied to this policy (none was applied to ASP036773136). Attachments read: Policy Letter, Policy Schedule, Direct Debit Service Agreement, Certificate of Currency. Both policy schedules answer 'sub-contractors or labour hire staff engaged at any one time: None' and 'Number of | O52: 19e1e4c6acffb4dc
A53: 2026-05-18 | B53: Dulux | C53: 0909118279 | D53: stock | E53: Materials & paint | F53: 53.95 | G53: 8.09 | H53: 62.04 | I53: Yes | K53: 2026-06-20 | L53: Paid | M53: Jun 2026 Dulux statement shows payment 20/06/2026 EFT $1,449.01 clearing the May 2026 balance (all 11 May invoices). | N53: Corroborated by Dulux monthly statement for account 146009. One of 5 invoices in a single email; PO/location taken from the May statement. GST split derived at 15% (total x 3/23); only the GST-inclusive total was stated in the email. | O53: 19e3c0bb2f521a4d
A54: 2026-05-18 | B54: Dulux | C54: 0909118555 | D54: 84 C aubary | E54: Materials & paint | F54: 42.88 | G54: 6.43 | H54: 49.31 | I54: Yes | K54: 2026-06-20 | L54: Paid | M54: Jun 2026 Dulux statement shows payment 20/06/2026 EFT $1,449.01 clearing the May 2026 balance (all 11 May invoices). | N54: Corroborated by Dulux monthly statement for account 146009. One of 5 invoices in a single email; PO/location taken from the May statement. GST split derived at 15% (total x 3/23); only the GST-inclusive total was stated in the email. | O54: 19e3c0bb2f521a4d
A55: 2026-05-18 | B55: Dulux | C55: 0909118566 | D55: 10 Mcloud av | E55: Materials & paint | F55: 51.83 | G55: 7.78 | H55: 59.61 | I55: Yes | K55: 2026-06-20 | L55: Paid | M55: Jun 2026 Dulux statement shows payment 20/06/2026 EFT $1,449.01 clearing the May 2026 balance (all 11 May invoices). | N55: Corroborated by Dulux monthly statement for account 146009. One of 5 invoices in a single email; PO/location taken from the May statement. GST split derived at 15% (total x 3/23); only the GST-inclusive total was stated in the email. | O55: 19e3c0bb2f521a4d
A56: 2026-05-18 | B56: Dulux | C56: 0909125287 | D56: 10 mcloud ave | E56: Materials & paint | F56: 87.4 | G56: 13.11 | H56: 100.51 | I56: Yes | K56: 2026-06-20 | L56: Paid | M56: Jun 2026 Dulux statement shows payment 20/06/2026 EFT $1,449.01 clearing the May 2026 balance (all 11 May invoices). | N56: Corroborated by Dulux monthly statement for account 146009. One of 5 invoices in a single email; PO/location taken from the May statement. GST split derived at 15% (total x 3/23); only the GST-inclusive total was stated in the email. | O56: 19e3c0bb2f521a4d
A57: 2026-05-18 | B57: Dulux | C57: 0909125389 | D57: stock | E57: Materials & paint | F57: 15.99 | G57: 2.4 | H57: 18.39 | I57: Yes | K57: 2026-06-20 | L57: Paid | M57: Jun 2026 Dulux statement shows payment 20/06/2026 EFT $1,449.01 clearing the May 2026 balance (all 11 May invoices). | N57: Corroborated by Dulux monthly statement for account 146009. One of 5 invoices in a single email; PO/location taken from the May statement. GST split derived at 15% (total x 3/23); only the GST-inclusive total was stated in the email. | O57: 19e3c0bb2f521a4d
A58: 2026-05-18 | B58: R&S Trade Centre Ltd | C58: 56035 | D58: Festool Granat Delta sanding discs (120g x50, 150g x30) + flat rate shipping | E58: Equipment | F58: 101.04 | G58: 15.16 | H58: 116.2 | I58: Yes | K58: 2026-05-18 | L58: Paid | M58: Order confirmation states 'Payment method: Payment Express' — paid online at time of order. | N58: Tax invoice PDF emailed 2026-05-19 (thread 19e3ccaf8731a5a8, filename Cin7_Order_254905_56035_19_May_2026). | O58: 19e375f6761455e9
A59: 2026-05-20 | B59: Pukka Ltd (Wanaka) | C59: INV/2026/00811 | D59: Signage — two signs produced from Lakeside Painting artwork (quote ref S05815, 'Signs'). Likely vehicle/site signage. | E59: Advertising & marketing | F59: 435 | G59: 65.25 | H59: 500.25 | I59: Yes | L59: Unknown | M59: Invoice asks for bank transfer to account 06-0943-0117749-00 quoting INV/2026/00811. Separate Pukka email 2026-05-20 ('Your job is completed') warns 'Non account holders must pay on pick up' — so this may have been PAID IN PERSON / ON PICKUP rather than by transfer. Worth checking the bank statement around 20 May 2026. | N59: Quote S05815 issued 2026-02-20 at the same $500.25; Brad formally accepted on 2026-05-12 ('Happy to go ahead with the signage'). Signwriting is confirmed as working — Riverslea PM commented 'Nice to hear the car signwriting is doing its job' (2026-07-02). | O59: 19e438a52f4b86c6
A60: 2026-05-22 | B60: Dulux | C60: 0909209638 | D60: 10 mcloud av | E60: Materials & paint | F60: 524.34 | G60: 78.65 | H60: 602.99 | I60: Yes | K60: 2026-06-20 | L60: Paid | M60: Jun 2026 Dulux statement shows payment 20/06/2026 EFT $1,449.01 clearing the May 2026 balance (all 11 May invoices). | N60: Corroborated by Dulux monthly statement for account 146009. One of 2 invoices in a single email; PO/location taken from the May statement. GST split derived at 15% (total x 3/23); only the GST-inclusive total was stated in the email. | O60: 19e50f0fd6302159
A61: 2026-05-22 | B61: Dulux | C61: 0909215128 | D61: 10 mcloud avenue | E61: Materials & paint | F61: 109.85 | G61: 16.48 | H61: 126.33 | I61: Yes | K61: 2026-06-20 | L61: Paid | M61: Jun 2026 Dulux statement shows payment 20/06/2026 EFT $1,449.01 clearing the May 2026 balance (all 11 May invoices). | N61: Corroborated by Dulux monthly statement for account 146009. One of 2 invoices in a single email; PO/location taken from the May statement. GST split derived at 15% (total x 3/23); only the GST-inclusive total was stated in the email. | O61: 19e50f0fd6302159
A62: 2026-05-25 | B62: Print It Wanaka | C62: INV/2026/00501 | D62: 100 double-sided business cards, 90x55mm, 350gsm silk coated stock (ref S04961) | E62: Advertising & marketing | F62: 100 | G62: 15 | H62: 115 | I62: Yes | L62: Unknown | M62: Invoice says 'Please remit payment at your earliest convenience' quoting INV/2026/00501. No payment confirmation in email. Print It and Pukka share the same phone number (03 443 7804) and Odoo system — likely the same business, so this may also have been paid on pickup. | N62: Ordered same day (2026-05-25) via print@pukka.nz thread 19e5bef7f03c0c8c. | O62: 19e5cf063546a79f
A63: 2026-05-28 | B63: Dulux | C63: 0909307380 | D63: CROMWELL RACETRACK | E63: Materials & paint | F63: 225.62 | G63: 33.84 | H63: 259.46 | I63: Yes | K63: 2026-06-20 | L63: Paid | M63: Jun 2026 Dulux statement shows payment 20/06/2026 EFT $1,449.01 clearing the May 2026 balance (all 11 May invoices). | N63: Corroborated by Dulux monthly statement for account 146009. Sent from noreply.duluxnz@e.duluxgroup.com.au (Account ***009). GST split derived at 15% (total x 3/23); only the GST-inclusive total was stated in the email. | O63: 19e6c0823b4385e0
A64: 2026-05-29 | B64: Dulux | C64: 0909327913 | D64: CROMWELL RESTRACK | E64: Materials & paint | F64: 24.89 | G64: 3.73 | H64: 28.62 | I64: Yes | K64: 2026-06-20 | L64: Paid | M64: Jun 2026 Dulux statement shows payment 20/06/2026 EFT $1,449.01 clearing the May 2026 balance (all 11 May invoices). | N64: Corroborated by Dulux monthly statement for account 146009. Sent from noreply.duluxnz@e.duluxgroup.com.au (Account ***009). PO shown as 'CROMWELL RESTRACK' (apparent typo for RACETRACK). GST split derived at 15% (total x 3/23); only the GST-inclusive total was stated in the email. | O64: 19e71602561d04e3
A65: 2026-05-31 | B65: Google New Zealand Limited | C65: 5586540330 | D65: Google Workspace Business Standard - commitment, service period 1 May 2026 to 31 May 2026, 1 seat. Domain lakesidepainting.co.nz. | E65: Software & subscriptions | F65: 15.75 | G65: 2.36 | H65: 18.11 | I65: Yes | K65: Auto-charged on/around 2026-06-02 | L65: Paid Automatically | M65: Automatic card charge; card not disclosed. | O65: 19e85e7b3d850224
A66: 2026-06-02 | B66: Dulux | C66: 0909367643 | D66: CROMWELL RACECOURSE | E66: Materials & paint | F66: 423.31 | G66: 63.5 | H66: 486.81 | I66: Yes | K66: 2026-07-20 | L66: Paid | M66: Jul 2026 Dulux statement (thread 19fbb368feaa27d0) shows payment 20/07/2026 EFT 146009 $498.52, clearing the Jun 2026 closing balance of $498.52 (both June invoices). | N66: Corroborated by Dulux monthly statement for account 146009. Sent from noreply.duluxnz@e.duluxgroup.com.au (Account ***009). GST split derived at 15% (total x 3/23); only the GST-inclusive total was stated in the email. | O66: 19e851db5c1c1fa9
A67: 2026-06-03 | B67: Dulux | C67: 0909398550 | D67: CROMWELL RACETRACK | E67: Materials & paint | F67: 10.18 | G67: 1.53 | H67: 11.71 | I67: Yes | K67: 2026-07-20 | L67: Paid | M67: Jul 2026 Dulux statement shows payment 20/07/2026 EFT $498.52 clearing the Jun 2026 balance (both June invoices). | N67: Corroborated by Dulux monthly statement for account 146009. Sent from noreply.duluxnz@e.duluxgroup.com.au (Account ***009). GST split derived at 15% (total x 3/23); only the GST-inclusive total was stated in the email. | O67: 19e8b17ea62c5f3b
A68: 2026-06-15 | B68: Wanaka Business Chamber (Wanaka & District Chamber of Commerce & Industry) | C68: INV-8210 | D68: Membership - Tier 1, 06/2026 to 05/2027. Membership number 200708, account reference 20184769. Billed to Lakeside Painting Limited, 35 Old Racecourse Road, Wanaka 9305. | E68: Software & subscriptions | F68: 275 | G68: 41.25 | H68: 316.25 | I68: Yes | L68: Unknown - Due 20 Jul 2026. No Remittance Or Payment Confirmation In The Mailbox. | M68: Invoice requests bank transfer to Wanaka & District Chamber of Commerce & Industry, Westpac 03 1739 0007205 00. No card or cash indicator. | N68: Correctly addressed to Lakeside Painting Limited. Prepaid 12-month membership straddling the balance date - may need apportioning. | O68: 19ec91d0871dcb2f
A69: 2026-06-17 | B69: Taskhound Limited, 10 Dow Close, Wanaka | C69: INV-0054 | D69: Lines: Vehicle and Technician 1 @ $40.00 charged at $0.00 (waived); Labour 6.75 hrs @ $75.00 = $506.25 - 'Remove and rebuild plywood base, tops and horizontal drawer'; Materials 1 @ $352.64 (screws, sealants, fittings and other consumables). Invoice | E69: Subcontractor | F69: 858.89 | G69: 128.84 | H69: 987.73 | I69: Yes | L69: Unknown - Invoice Due 24 Jun 2026. No Remittance, Receipt Or Payment Confirmation Exists In The Mailbox. | M69: Invoice requests bank deposit to Taskhound Limited, Kiwibank 38-9027-0333199-00, using the invoice number as reference. No card or cash indicator. | N69: FLAG FOR REVIEW: the invoice reference is '35 Old Racecourse rd', which is Bradley Hamilton's home/business address, and the work described (remove and rebuild plywood base, tops and horizontal drawer) is joinery/cabinetry rather than painting. Worth confirming with Brad whether this is a business or private expense, and whether it should be capitalised. Terms: payment within 7 days, 1.5% per mont | O69: 19ed5375598f2089
A70: 2026-06-22 | B70: Trademax NZ Limited | C70: WAN7942 | D70: Gib Tradeset 45 5kg bag, mixing paddle, 2 x 10L paint pails | E70: Materials & paint | F70: 46.47 | G70: 6.97 | H70: 53.45 | I70: Yes | K70: 2026-07-20 | L70: Paid | M70: Stripe receipt #1520-0614, NZ$347.90 paid 20 Jul 2026, summary: 'Statement payment for invoice(s): WANAKA - WAN7942, WANAKA - WAN8213' (53.45 + 294.45 = 347.90). Stripe thread 19f7c2350cba1240. | N70: Figures as printed on the receipt. Note the receipt's own rounding: subtotal $46.47 + GST $6.97 = $53.44, but the printed TOTAL and the Xero invoice both say $53.45 (Lightspeed rounds per line). Use $53.45. Mixed materials/consumables. Lightspeed #WAN7942 = Xero 'WANAKA - WAN7942'. | O70: 19eed0f5b24db4f1
A71: 2026-06-26 | B71: Resene | C71: 424763500 | D71: 45 LINTON AVE | E71: Materials & paint | F71: 102.09 | G71: 15.31 | H71: 117.4 | I71: Yes | K71: 2026-07-20 | L71: Paid | M71: Resene 'Payment made to MyResene' email 20/07/2026 (thread 19f7d844ca47808d) lists this invoice paid in full by Direct Debit, balance $0.00; matching 'Payment agreement made MyResene' email 19/07/2026 (thread 19f7c1fe1733ec61). Total run $490.03. | N71: Total $117.40 stated in the body of the accounts@resene.co.nz 'Resene | Invoice 424763500' email (thread 19f856c083156e34, 21/07/2026) and in the payment emails. Original e-invoice email 26/06/2026 (thread 19f02fdc3d7ee6ca) had the amount in the PDF only. Due 20/07/2026. GST split read from the attached PDF. | O71: 19f02fdc3d7ee6ca
A72: 2026-06-29 | B72: Resene | C72: 424769024 | D72: 32 ASH AVENUE | E72: Materials & paint | F72: 231.01 | G72: 34.65 | H72: 265.66 | I72: Yes | K72: 2026-07-20 | L72: Paid | M72: Resene 'Payment made to MyResene' email 20/07/2026 (thread 19f7d844ca47808d) lists this invoice paid in full by Direct Debit, balance $0.00; matching 'Payment agreement made MyResene' email 19/07/2026 (thread 19f7c1fe1733ec61). Total run $490.03. | N72: Total $265.66 stated in the body of the accounts@resene.co.nz email (thread 19f856c081d8eb15, 21/07/2026) and in the payment emails. Due 20/07/2026. GST split read from the attached PDF. | O72: 19f12755541d19f3
A73: 2026-06-30 | B73: Resene | C73: 424771838 | D73: 32 ASH AVE | E73: Materials & paint | F73: 93.02 | G73: 13.95 | H73: 106.97 | I73: Yes | K73: 2026-07-20 | L73: Paid | M73: Resene 'Payment made to MyResene' email 20/07/2026 (thread 19f7d844ca47808d) lists this invoice paid in full by Direct Debit, balance $0.00; matching 'Payment agreement made MyResene' email 19/07/2026 (thread 19f7c1fe1733ec61). Total run $490.03. | N73: Total $106.97 stated in the body of the accounts@resene.co.nz email (thread 19f856c07e60af93, 21/07/2026) and in the payment emails. Due 20/07/2026. GST split read from the attached PDF. | O73: 19f179cf836ee96b
A74: 2026-06-30 | B74: Trademax NZ Limited | C74: WAN8213 | D74: Bisley Flex & Move zip utility cargo pant (stone, size 87), PUMA Tanami pull-on boot (brown, UK9) | E74: Workwear & PPE | F74: 256.04 | G74: 38.41 | H74: 294.45 | I74: Yes | K74: 2026-07-20 | L74: Paid | M74: Stripe receipt #1520-0614, NZ$347.90 paid 20 Jul 2026, summary: 'Statement payment for invoice(s): WANAKA - WAN7942, WANAKA - WAN8213' (53.45 + 294.45 = 347.90). Stripe thread 19f7c2350cba1240. | N74: Receipt Note reads 'Clothing'. The Xero thread 19f1acfaf2099649 holds two identical Xero sends of the same invoice (6 min apart) plus Brad's forward to the bookkeeping inbox - one purchase, not three. Lightspeed #WAN8213 = Xero 'WANAKA - WAN8213'. | O74: 19f156141415ee1d
A75: 2026-06-30 | B75: Google New Zealand Limited | C75: 5607652125 | D75: Google Workspace Business Standard - commitment, service period 1 Jun 2026 to 30 Jun 2026, 1 seat. Domain lakesidepainting.co.nz. | E75: Software & subscriptions | F75: 19.78 | G75: 2.97 | H75: 22.75 | I75: Yes | K75: Auto-charged on/around 2026-07-01 | L75: Paid Automatically | M75: Automatic card charge; card not disclosed. | N75: Higher than April/May because Google notified a Business Standard price change effective 8 June 2026 (thread 19e81fcd39068c5f). Running total for the 4 Google Workspace invoices in scope: $73.00 incl GST ($63.47 excl GST, $9.52 GST). No July invoice had arrived by 31 July 2026. | O75: 19f1d46b3c023219
A76: 2026-07-13 | B76: Dulux | C76: 0910038623 | D76: 4 perrow street | E76: Materials & paint | F76: 128.37 | G76: 19.25 | H76: 147.62 | I76: Yes | L76: Unpaid | M76: Jul 2026 Dulux statement (issued 01/08/2026) still shows this invoice as Current with an account balance of $172.35 outstanding; no payment recorded up to 31/07/2026. | N76: Corroborated by Dulux monthly statement for account 146009. Sent from noreply.duluxnz@e.duluxgroup.com.au (Account ***009). GST split derived at 15% (total x 3/23); only the GST-inclusive total was stated in the email. | O76: 19f58b0697c8e337
A77: 2026-07-13 | B77: Resene | C77: 425300832 | D77: 4 PERROW ST | E77: Materials & paint | F77: 315 | G77: 47.25 | H77: 362.25 | I77: Yes | L77: Unpaid | M77: Due for payment 20/08/2026 per the accounts@resene.co.nz email. No payment email found on or before 31/07/2026. | N77: Total $362.25 stated in the body of the accounts@resene.co.nz email (thread 19f856c0602976f3, 21/07/2026). Original e-invoice email 13/07/2026. GST split read from the attached PDF. | O77: 19f5a8d89578e7f4
A78: 2026-07-16 | B78: Dulux | C78: 0910113487 | D78: 4 pero street | E78: Materials & paint | F78: 21.5 | G78: 3.23 | H78: 24.73 | I78: Yes | L78: Unpaid | M78: Jul 2026 Dulux statement (issued 01/08/2026) still shows this invoice as Current with an account balance of $172.35 outstanding; no payment recorded up to 31/07/2026. | N78: Corroborated by Dulux monthly statement for account 146009. Sent from noreply.duluxnz@e.duluxgroup.com.au (Account ***009). PO shown as '4 pero street' (apparent typo for Perrow). GST split derived at 15% (total x 3/23); only the GST-inclusive total was stated in the email. | O78: 19f690360ee2253f
A79: 2026-07-16 | B79: Resene | C79: 425310813 | D79: 4 PERROW ST | E79: Materials & paint | F79: 128.92 | G79: 19.34 | H79: 148.26 | I79: Yes | L79: Unpaid | M79: Due for payment 20/08/2026 per the accounts@resene.co.nz email. No payment email found on or before 31/07/2026. | N79: Total $148.26 stated in the body of the accounts@resene.co.nz email (thread 19f856c03f919bf9, 21/07/2026). Original e-invoice email 16/07/2026. GST split read from the attached PDF. | O79: 19f6a01d0d59ff01
A80: 2026-07-20 | B80: Resene | C80: 425319907 | D80: 7 CAIRNMUIR ST | E80: Materials & paint | F80: 182.12 | G80: 27.32 | H80: 209.44 | I80: Yes | L80: Unpaid | M80: Due for payment 20/08/2026 per the accounts@resene.co.nz email. No payment email found on or before 31/07/2026. | N80: Total $209.44 stated in the body of the accounts@resene.co.nz email. No separate einvoice@resene.co.nz e-invoice email was found for this invoice - it only arrived in the 21/07/2026 accounts@ batch. GST split read from the attached PDF. | O80: 19f856c02e49afd9
E82: TOTAL | F82: =SUM(F6:F80) -> 15524.27 | G82: =SUM(G6:G80) -> 2328.68 | H82: =SUM(H6:H80) -> 17852.96
B84: BY CATEGORY
B85: Category | F85: Ex GST | G85: GST | H85: Incl GST
B86: Advertising & marketing | F86: =SUMIF($E$6:$E$80,$B86,$F$6:$F$80) -> 535 | G86: =SUMIF($E$6:$E$80,$B86,$G$6:$G$80) -> 80.25 | H86: =SUMIF($E$6:$E$80,$B86,$H$6:$H$80) -> 615.25
B87: Consumables | F87: =SUMIF($E$6:$E$80,$B87,$F$6:$F$80) -> 196.48 | G87: =SUMIF($E$6:$E$80,$B87,$G$6:$G$80) -> 29.48 | H87: =SUMIF($E$6:$E$80,$B87,$H$6:$H$80) -> 225.96
B88: Equipment | F88: =SUMIF($E$6:$E$80,$B88,$F$6:$F$80) -> 3508.03 | G88: =SUMIF($E$6:$E$80,$B88,$G$6:$G$80) -> 526.22 | H88: =SUMIF($E$6:$E$80,$B88,$H$6:$H$80) -> 4034.25
B89: Equipment Hire | F89: =SUMIF($E$6:$E$80,$B89,$F$6:$F$80) -> 147.89 | G89: =SUMIF($E$6:$E$80,$B89,$G$6:$G$80) -> 22.19 | H89: =SUMIF($E$6:$E$80,$B89,$H$6:$H$80) -> 170.08
B90: Insurance | F90: =SUMIF($E$6:$E$80,$B90,$F$6:$F$80) -> 1462.54 | G90: =SUMIF($E$6:$E$80,$B90,$G$6:$G$80) -> 219.38 | H90: =SUMIF($E$6:$E$80,$B90,$H$6:$H$80) -> 1681.92
B91: Materials & paint | F91: =SUMIF($E$6:$E$80,$B91,$F$6:$F$80) -> 7880.93 | G91: =SUMIF($E$6:$E$80,$B91,$G$6:$G$80) -> 1182.14 | H91: =SUMIF($E$6:$E$80,$B91,$H$6:$H$80) -> 9063.08
B92: Software & subscriptions | F92: =SUMIF($E$6:$E$80,$B92,$F$6:$F$80) -> 338.47 | G92: =SUMIF($E$6:$E$80,$B92,$G$6:$G$80) -> 50.77 | H92: =SUMIF($E$6:$E$80,$B92,$H$6:$H$80) -> 389.24
B93: Subcontractor | F93: =SUMIF($E$6:$E$80,$B93,$F$6:$F$80) -> 1198.89 | G93: =SUMIF($E$6:$E$80,$B93,$G$6:$G$80) -> 179.84 | H93: =SUMIF($E$6:$E$80,$B93,$H$6:$H$80) -> 1378.73
B94: Workwear & PPE | F94: =SUMIF($E$6:$E$80,$B94,$F$6:$F$80) -> 256.04 | G94: =SUMIF($E$6:$E$80,$B94,$G$6:$G$80) -> 38.41 | H94: =SUMIF($E$6:$E$80,$B94,$H$6:$H$80) -> 294.45
B95: Total | F95: =SUM(F86:F94) -> 15524.27 | G95: =SUM(G86:G94) -> 2328.68 | H95: =SUM(H86:H94) -> 17852.96

Sheet Credit Notes & Adjustments
A1: Credit Notes, Adjustments, Cancellations & Doubtful Debts
A2: Everything that changes, reverses or casts doubt on an invoice in the period. Read this before booking the invoice tabs.
A5: Date | B5: Side | C5: Party | D5: Job | E5: Type | F5: Effect on income/cost (incl GST) | G5: What happened | H5: Action for the accountant
A6: 2026-01-30 | B6: Customer | C6: Craig Chirnside | D6: 18 Hewson Crescent, Lake Hawea | E6: Price Reduction | F6: -345 | G6: Scaffold hire of $300 (+GST) removed from the final invoice because scaffolding was not needed. Job total reduced from $2,770 + GST to $2,470 + GST. | H6: Confirm the figure and that it reached the ledger.
A7: 2026-02-08 | B7: Customer | C7: Pennie Jackson | D7: Flat repaint, Wanaka | E7: Cost Absorbed No Charge | F7: 0 | G7: Job took 5 days on site instead of the quoted 3, with substantial extra prep and two coats where one was quoted. Lakeside honoured the original quoted price and charged no variation. | H7: Verified from email.
A8: 2026-03-14 | B8: Customer | C8: Glenda Turner | D8: 29 Tomtit Crescent, Lake Hawea - retaining wall | E8: Variation Up | F8: 138 | G8: Wall area larger than quoted (section continued behind the gate). Extra 4L Resene Lumbersider charged at $120 on the final invoice; the additional labour was NOT charged. Not stated whether the $120 is GST-inclusive or exclusive. | H8: Confirm the figure and that it reached the ledger.
A9: 2026-04-07 | B9: Customer | C9: Home & Co. Property Management Ltd (Toni Fox) / property owner | D9: Cedar restain - believed to be 3 Merivale Avenue | E9: Variation Up Approved | F9: 2300 | G9: Additional $2,000 + GST ($2,300 incl) approved for extra prep after the old film-forming coating was found to be delaminating and chemically incompatible with the oil stain on the sun-exposed elevations. Requested 2 Apr 2026 (thread 19d4c8d493328bb0), approved 7 Apr 2026. CAUTION: the approval arrived as a reply inside the 10 McLeod Avenue thread (19d5efa8fce440b0) even though the work described is the 3 Merivale Avenue restain - confirm which job it was billed to. | H9: Verified from email.
A10: 2026-05-18 | B10: Customer | C10: Kevin Henderson | D10: 3 Parkview Street - interior repaint | E10: Job Cancelled After Invoicing | F10: -5057.7 | G10: Deposit invoice for $5,057.70 incl GST issued 26 Apr 2026. On 19 May 2026 (NZ) the customer advised the house had been sold and the job would not proceed; no work had started. Brad accepted the cancellation without comment on the deposit. NO credit note, refund or write-off appears in the mailbox. Needs resolution: was the deposit received, and is it being refunded, retained, or credited? | H10: Verified from email.
A11: 2026-05-06 | B11: Customer | C11: Rebecca Maplesden | D11: 32 Malvern Road - cedar staining | E11: Job Repriced Down After Period | F11: -921.15 | G11: Job repriced from $3,450 incl GST to $2,528.85 incl GST after switching to a one-coat Dryden WoodOil approach. Final invoice INV-Q032-final issued 6 May 2026 for the $1,493.85 incl GST balance (OUTSIDE this period). Affects the in-period deposit invoice of $1,035 incl GST. Rebecca confirmed on 8 May 2026: 'The full invoice has been paid.' | H11: Verified from email.
A12: 2026-04-28 | B12: Customer | C12: Kevin Henderson and Troy Nicholson | D12: 3 Parkview Street deposit (26 Apr) and 4 Perrow Street ceiling deposit (28 Apr) | E12: Invoice Reference Clash | G12: Two DIFFERENT deposit invoices to two DIFFERENT customers were sent two days apart with the identical attachment filename 'INV-Q034-deposit.pdf'. Separately, the quote reference 'QUO-034' was also used for the Central Lakes Equestrian Club Administration Building quote of 15 Apr 2026 ($5,200 + GST). The quote/invoice numbering appears to have been reused across at least three unrelated jobs. Check the actual invoice numbers inside the PDFs and correct/re-issue if duplicated. | H12: Verified from email.
A13: 2026-03-04 | B13: Customer | C13: Latch Build Ltd | D13: 1 Ivy Lane - bathroom repair paint works | E13: Invoice Defect | G13: Invoice was issued with no payment due date. Latch Build applied their default of the 20th of the following month before agreeing to pull it back. No credit note; noted as an invoicing-process issue only. | H13: Verified from email.
A14: 2026-07-23 | B14: Customer | C14: Home & Co. Property Management Ltd (Jessica Patrick) | D14: 7 Cairnmuir Street | E14: Invoice Reissued Gst Error | F14: -298.42 | G14: GST was charged twice. Deposit invoice INV-8836EB was issued for $686.38 incl GST when the intended deposit was $596.85 (30% of the $1,989.50 GST-inclusive agreed price); the customer paid $686.38. Final invoice INV-Q040 was then first issued at $1,601.54 incl GST, which repeated the error. Brad acknowledged the mistake the same day ('Good pickup, that needs sorting. My mistake.') and re-issued INV-Q040 at the corrected $1,303.12 incl GST. A third, cosmetically-tidied copy of the same corrected invoice was sent an hour later. | No formal credit note was issued - the invoice was simply replaced. If the accounting system holds the $1,601.54 version, it needs correcting. | H14: Check which version of the invoice is in the ledger and correct if needed.
A15: 2026-05-27 | B15: Customer | C15: Central Lakes Equestrian Club Inc | D15: Administration Building, Cromwell Racecourse Reserve | E15: Invoice Reissued Bank Details | F15: 0 | G15: Deposit invoice re-issued with corrected bank account details after the Club's Treasurer's payment of $1,794 was rejected ('the system said the account number is invalid'). The original showed an out-of-date ANZ account from an old template; the revised version shows BNZ 02-0312-0183213-000, Lakeside Painting Limited. No change to the amount. | There may be an equivalent problem on any other invoice issued from the same old template before 27 May 2026 - worth checking with Brad. | H15: Check which version of the invoice is in the ledger and correct if needed.
A16: 2026-05-19 | B16: Customer | C16: Kevin Henderson | D16: 3 Parkview Street - interior repaint | E16: Job Cancelled After Invoicing | F16: -5057.7 | G16: Deposit invoice for $5,057.70 incl GST (30% deposit) was issued 26 April 2026. The customer never paid it, and on 19 May 2026 (NZ) cancelled the job entirely: 'We just had someone come and buy the house ... They bought the property as is so unfortunately we don't need the house painted.' Brad accepted the cancellation with no charge. The invoice should be voided/cancelled if it is still open in the ledger. | Invoice DATE (26 Apr 2026) is outside the May-July window so it is not listed as an invoice above, but the cancellation event falls inside the period and is material ($5,057.70). This is a cancellation, not a bad debt - nothing was ever paid and no work was done. Note the invoice reference INV-Q034-deposit is confusingly similar to the Central Lakes Equestrian Club's INV-034-DEP for a completely different customer. | H16: Check which version of the invoice is in the ledger and correct if needed.
A17: 2026-05-06 | B17: Customer | C17: Rebecca Maplesden | D17: 32 Malvern Rd - cedar staining | E17: Job Repriced Before Invoicing | F17: -921.15 | G17: Job re-priced downward from the original $3,450.00 incl GST quote to $2,528.85 incl GST after changing method to a single-coat Dryden WoodOil maintenance coat. This is a quote revision, not a credit note - the final invoice was raised at the reduced figure. | Recorded for context only; no adjustment entry should be needed. | H17: Check which version of the invoice is in the ledger and correct if needed.
A18: 2026-04-26 | B18: Customer | C18: Steven Jin | D18: Pizza Hut Wanaka - plastering and painting of wall and bulkhead | E18: Possible Outstanding Receivable Outside Period | F18: 0 | G18: Invoice for $2,559.00 + GST = $2,942.85 incl GST emailed 26 April 2026 (NZ). No payment confirmation, remittance or follow-up about payment appears anywhere in the mailbox, including a later June exchange with the same customer (which was only about a Google review). | OUT OF SCOPE for the May-July invoice list (invoice dated April), but flagged because it is the only sizeable customer invoice in the mailbox with no trace of payment. Worth checking against the bank account for an aged receivable. | H18: Check which version of the invoice is in the ledger and correct if needed.
B19: Customer | C19: Multiple | E19: Document Numbering Risk | F19: 0 | G19: Quote number QUO-034 was used for TWO different customers - Troy Nicholson (4 Perrow Street, quoted 26 April 2026 at $3,450 + GST) and Central Lakes Equestrian Club (Administration Building, quoted 15 April 2026 at $5,200 + GST). The resulting invoice references are near-identical: INV-Q034-deposit (Nicholson) vs INV-034-DEP / INV-034-FIN (CLEC). Quote number QUO-037 was also reused (Emily Sancha, 3 Riverhaven Lane; and Jac Macdonald/Amrein, 31 Hewson Crescent). | High risk of mis-posting between these two customers. Also note invoice numbering across the period is inconsistent (INV-Q032-final, INV-CC-001, INV-028-Final, INV-034-DEP, INV-B43C21, INV-8836EB, INV-J20-F, INV-Q040) and two invoices carry no visible number at all. | H19: Check which version of the invoice is in the ledger and correct if needed.
A20: 2026-04-26 | B20: Customer | C20: Kevin Henderson | D20: 3 Parkview Street - interior repaint | E20: Cancelled After Invoicing | F20: -5057.7 | G20: Deposit invoice issued 26 Apr 2026; job cancelled 19 May 2026 (NZ) because the house sold before work started. No credit note or refund seen. Payment of the deposit itself was never confirmed in email. | H20: Void or credit this invoice — it is not income.
B21: Customer | C21: Kevin Henderson | D21: 3 Parkview Street | E21: No Payment Evidence | G21: INV-Q034-deposit — $5,057.70 incl GST. cancelled - never paid, job cancelled 19 May 2026 after the house sold. Not a bad debt; the invoice should be voided. | H21: Check the bank statement; write off or chase.
B22: Customer | C22: UCL Commercial Ltd (Steven Jin) | D22: Pizza Hut Wanaka | E22: No Payment Evidence | G22: INV-PHW — $2,942.85 incl GST. no payment evidence in the mailbox (invoice dated 26 April 2026, outside the reporting period). Possible aged receivable - check the bank. | H22: Check the bank statement; write off or chase.
B23: Customer | C23: Central Lakes Equestrian Club Inc | D23: Administration Building, Cromwell | E23: No Payment Evidence | G23: INV-034-DEP and INV-034-FIN — $5,980.00 incl GST. no payment confirmation for either invoice in the mailbox. The deposit payment attempt on 26 May 2026 FAILED because of wrong bank details on the invoice; the corrected invoice was sent 27 May but no confirmation of successful payment follows. The final invoice was passed to the Club Treasurer on 8 June with no payment confirmation. Verify against the bank. | H23: Check the bank statement; write off or chase.
A24: 2026-02-19 | B24: Customer | C24: Liam / LC Decorating | E24: No Payment Evidence | G24: Empty email body, PDF only. No amount, no reply, no payment reference at all. Highest-risk gap. | H24: Check the bank statement; chase if unpaid.
A25: 2026-03-04 | B25: Customer | C25: Danya Meakins | E25: No Payment Evidence | G25: 56 Dale Street final invoice - no reply in thread. | H25: Check the bank statement; chase if unpaid.
A26: 2026-03-17 | B26: Customer | C26: Wes and Ailsa | E26: No Payment Evidence | G26: Bathroom wallpapering invoice - no reply in thread. | H26: Check the bank statement; chase if unpaid.
A27: 2026-03-25 | B27: Customer | C27: Hilary Waller | E27: No Payment Evidence | G27: INV-J7-FINAL for the completed exterior work - single-message thread, no reply, no payment reference anywhere. Only the 20% deposit is confirmed paid. | H27: Check the bank statement; chase if unpaid.
A28: 2026-04-08 | B28: Customer | C28: Leigh Cashen / Riverstone | E28: No Payment Evidence | G28: 9 Hikuwai Drive wallpaper - no reply in thread. | H28: Check the bank statement; chase if unpaid.
A29: 2026-04-25 | B29: Customer | C29: UCL Commercial Ltd (Pizza Hut Wanaka) | E29: No Payment Evidence | G29: $2,942.85 incl GST. Later June 2026 contact was about a Google review only, with no mention of payment. | H29: Check the bank statement; chase if unpaid.
A30: 2026-03-24 / 2026-04-05 / 2026-04-22 | B30: Customer | C30: Home & Co. Property Management Ltd | E30: No Payment Evidence | G30: INV-J12, INV-027 and INV-J12-F. Toni Fox confirmed she would 'process' the 3 Merivale deposit and pays out on the 1st and 15th of the month, but no payment confirmations appear. Separately, on 25 May 2026 Home & Co advised the owner's account was short for the (out-of-period) 10 McLeod final invoice and asked to defer payment to the 15th - Brad agreed, so watch that account for slow payment. | H30: Check the bank statement; chase if unpaid.
A31: 2026-03-04 | B31: Customer | C31: Cam / Latch Build Ltd | E31: No Payment Evidence | G31: Acknowledged and entered into their system on 15 Mar 2026 and pulled forward to March, but no payment confirmation. | H31: Check the bank statement; chase if unpaid.
A32: 2026-02-25 | B32: Customer | C32: Sarah Gunn | E32: No Payment Evidence | G32: 50 Dale Street 40% progress invoice - customer said payment would go through 'shortly' but no receipt confirmation was found for this specific invoice (the final invoice was confirmed received). | H32: Check the bank statement; chase if unpaid.
A33: 2026-02-20 | B33: Supplier | C33: Trademax NZ Limited | E33: Supplier Refund / Credit Note | F33: -172.5 | G33: RETURN: 1 x Easy Access 3-step double-sided ladder 0.9m (OXDS03) | CREDIT NOTE. Lightspeed receipt #3909 shows qty -1, subtotal -$150.00, GST -$22.50, TOTAL -$172.50. Returns the 3-step ladder bought on #3013 (23 Jan 2026). The Xero email is worded 'Here's invoice WANAKA - 3909 for NZD 172.50' but its attachment is named 'Credit Note WANAKA - 3909.pdf', and the 28 Feb 2026 statement arithmetic confirms it is a credit: 54.60 + 47.50 + 308.57 - 172.50 = 238.17. Recorded here as -172.50. | H33: Offset against the original purchase — do not book as a cost.
A34: 2026-03-30 | B34: Supplier | C34: Trademax NZ Limited | D34: refund | E34: Supplier Refund / Credit Note | F34: -102.47 | G34: REFUND: 50 x Norton No-Fil SG 125mm 60G sanding discs | CREDIT NOTE / REFUND. Lightspeed receipt #5175 shows qty -50, subtotal -$89.10, GST -$13.37, TOTAL -$102.47, Note: 'refund'. Reverses #5173 issued 47 minutes earlier the same day. | H34: Offset against the original purchase — do not book as a cost.
A35: 2026-03-13 / 2026-04-02 | B35: Supplier | C35: Dulux | D35: PO 113 R3 | E35: Duplicate Billing — Unresolved | F35: -2907.14 | G35: Two identical $1,453.57 invoices (0908015736 and 0908369599) for the same PO. The first was deliberately excluded from the 19 Apr payment; the second appears on no statement at all. No credit note was ever emailed. | H35: CRITICAL: confirm with Dulux before booking either. Up to $2,907.14 of the Dulux total may not be a real cost.
E37: Net effect of quantified items | F37: =SUM(F6:F35) -> -18402.93

Sheet Gaps & Follow-ups
A1: Gaps, Missing Records & Follow-ups
A2: What is NOT in the email trail, what was paid personally or in cash, and what needs chasing. 19 Jan – 31 Jul 2026.
A5: Priority | B5: Area | C5: What is missing or wrong | D5: Why it matters | E5: Where to get it | F5: Status in mailbox
A6: HIGH | B6: Fuel | C6: No fuel receipts of any kind — no Z, BP, Mobil, Caltex, Gull, Allied, no fuel card statement, no road user charges (RUC). | D6: A painting business running a van across Wanaka, Cromwell and Queenstown for 6 months must have fuel cost. Its complete absence means expenses and GST claimed are understated. | E6: Bank/credit-card statements; the fuel card provider; NZTA for RUC. | F6: Searched exhaustively — genuinely absent
A7: HIGH | B7: Phone & internet | C7: No telco bill at all — no One NZ, Spark, 2degrees, Skinny, Vodafone, Starlink, no broadband. | D7: The mobile 0221060336 is on every quote and email signature, so the cost exists. Likely on a personal account and never claimed. | E7: Personal bank statement or the telco portal. Decide the business-use split. | F7: Searched exhaustively — genuinely absent
A8: HIGH | B8: ACC levies | C8: No ACC invoice, CoverPlus / CoverPlus Extra notice or statement anywhere. | D8: ACC levies are a deductible business cost and a compliance obligation. ACC is not corresponding with this address at all. | E8: myACC account, or ACC directly. | F8: Genuinely absent
A9: HIGH | B9: IRD — GST registration backdating | C9: A 14 May 2026 IRD letter titled "Backdating your GST registration – requested information not provided" was never resolved in email. A "GST registration confirmed" letter followed on 26 May. | D9: The effective GST registration date decides whether input GST on earlier purchases is claimable at all. Until it is confirmed, every GST figure in this pack is provisional. | E9: Log into myIR and open the 14 May and 26 May letters. This is the single most important item here. | F9: 9 IRD alert emails, all contentless
A10: HIGH | B10: Dulux — possible duplicate billing | C10: Two identical $1,453.57 invoices for the same PO "113 R3" (0908015736 on 13 Mar, 0908369599 on 2 Apr). The first was excluded from the April payment; the second appears on no statement. No credit note was ever emailed. | D10: Up to $2,907.14 of the Dulux total may not be a real cost. Booking both would overstate expenses and overclaim GST. | E10: Call Dulux and ask for the account history for 146009. | F10: Both invoices are in the Supplier Bills tab — flagged
A11: HIGH | B11: One customer invoice has no figure | C11: INV-028-Final (Toni Fox / Home & Co, 10 McLeod Ave, 21 May 2026). The PDF is attached alongside large photos and could not be retrieved; no figure exists anywhere else. | D11: Income for the period is understated by this invoice. It is also the only remaining candidate for a second double-GST error. | E11: Open the email in Gmail and save the attachment, or check the bank for the receipt. | F11: Invoice listed with a blank amount
A12: HIGH | B12: Insurance paid on a personal card, wrong entity | C12: AA policy ASP036773136 (Jan–Mar) was in the name of RANK HIGHER LIMITED, not Lakeside, and was direct-debited from Bradley Hamilton's PERSONAL Visa ending 7490. It lapsed for non-payment; policy ASP036836160 replaced it from 13 May in Lakeside's name. | D12: Premiums paid personally for another entity are questionable as a Lakeside deduction. There is also an apparent gap in cover from about 21 Mar to 13 May 2026. | E12: Confirm cancellation with AA (0800 500 213) and decide the correct treatment of the $832.62. | F12: Both policies are in the Supplier Bills tab
A13: MEDIUM | B13: Vehicle costs | C13: No vehicle invoice at all — no rego, WOF, tyres, servicing or AA membership. Note the van KAJ960 was transferred to Bradley Hamilton PERSONALLY on 25 Feb 2026, yet the company insured it from 13 May. | D13: Ownership sitting with the individual while the company pays the costs affects how those costs are claimed. | E13: Card statements; GWD Toyota and Wanaka Auto Repairs for invoices; NZTA for rego. | F13: Only a service reminder and one estimate
A14: MEDIUM | B14: Bank & merchant fees | C14: No bank statements, bank fees or merchant service fees reach this mailbox. | D14: Bank fees are deductible; more importantly the bank statement is the only way to confirm the many payments marked "unknown" in this pack. | E14: Download the ANZ/BNZ statements for the period. | F14: Genuinely absent
A15: MEDIUM | B15: Subcontract labour | C15: Only Taskhound Limited invoiced Lakeside ($391.00 and $987.73) and neither is a painter. Yet Brad was advertising for staff and trialling workers through the period. | D15: If anyone was paid in cash or by private arrangement there may be unrecorded labour cost and PAYE/contractor-withholding obligations. | E15: Ask Brad directly what labour was paid and how. | F15: No individual painter invoices exist
A16: MEDIUM | B16: Software & subscriptions | C16: Google Workspace is the only software supplier billing this mailbox ($73.00 total). No Xero, hosting, domain renewal, Adobe, Canva or AI subscriptions. | D16: Two live websites exist (lakesidepainting.co.nz and painterswanaka.co.nz) so hosting and domain costs must be paid somewhere — likely a personal card. | E16: Card statements; ask Rank Higher what it charges for the SEO/hosting arrangement. | F16: Only 4 Google Workspace invoices
... A22: LOW | B22: TradePilot export is partial | C22: The TradePilot snapshot on the Desktop covers 18 Jan – 9 Apr 2026 only and is labelled "Sandbox". Everything from 10 Apr onward in this pack comes from email alone. | D22: Cross-checking is only possible for the first third of the period. | E22: Re-export TradePilot for the full period. | F22: Snapshot dated 29 Apr 2026

Sheet Supplier Statements
A1: Supplier Statements on File
A2: Use these to reconcile the Supplier Bills tab. Statements are the supplier’s own record of what was owed.
A5: Supplier | B5: Statement month / date | C5: Account ref | D5: Closing balance | E5: Overdue | F5: Notes
A6: Dulux | B6: 2026-01 | C6: Dulux account 146009 | D6: 216.85 | F6: Jan 2026: 1 transaction (0907154714 $216.85). Overdue 0.00, Current 216.85, Not Yet Due 0.00. No payments allocated in January.
A7: Dulux | B7: 2026-02 | C7: Dulux account 146009 | D7: 1076.85 | F7: Feb 2026: 8 invoices totalling $1,076.85. Payment allocated 14/02/2026 EFT 146009 $216.85 (cleared the January balance).
A8: Dulux | B8: 2026-03 | C8: Dulux account 146009 | D8: 1655.88 | F8: Mar 2026: 5 invoices totalling $1,655.88 (incl. 0908015736 $1,453.57). Payment allocated 18/03/2026 EFT 146009 $1,076.85 (cleared the February balance).
A9: Dulux | B9: 2026-04 | C9: Dulux account 146009 | D9: 365.26 | F9: Apr 2026: 3 invoices totalling $365.26. Payment allocated 19/04/2026 EFT 146009 $202.31 (= March total less invoice 0908015736). Invoice 0908369599 dated 02/04/2026 ($1,453.57) does NOT appear on this statement.
A10: Dulux | B10: 2026-05 | C10: Dulux account 146009 | D10: 1449.01 | F10: May 2026: 11 invoices totalling $1,449.01. Payment allocated 18/05/2026 EFT 146009 $365.26 (cleared the April balance).
A11: Dulux | B11: 2026-06 | C11: Dulux account 146009 | D11: 498.52 | F11: Jun 2026: 2 invoices totalling $498.52. Payment allocated 20/06/2026 EFT 146009 $1,449.01 (cleared the May balance).
A12: Dulux | B12: 2026-07 | C12: Dulux account 146009 | D12: 172.35 | F12: Jul 2026: 2 invoices totalling $172.35, still outstanding. Payment allocated 20/07/2026 EFT 146009 $498.52 (cleared the June balance).
A13: Trademax NZ Limited | B13: 2026-01-31 | D13: 1201.86 | F13: 'Outstanding statement as at 31 January 2026 - $1201.86 Due'. PDF 'Statement for Lakeside Painting As At 31Jan2026.pdf' attached (not opened). Equals invoices 2905 + 3013 + 3023 + 3118 + 3119. Settled 14 Feb 2026.
A14: Trademax NZ Limited | B14: 2026-02-28 | D14: 238.17 | F14: 'Outstanding statement as at 28 February 2026 - $238.17 Due'. Equals 3333 + 3397 + 3910 less credit note 3909 (54.60 + 47.50 + 308.57 - 172.50). Cleared during March 2026 - no payment receipt on file.
A15: Trademax NZ Limited | B15: 2026-03-31 | D15: 219.34 | F15: 'Outstanding statement as at 31 March 2026 - $219.34 Balance due'. Equals 4224 + 4262. Note receipts 5173/5175 (30 Mar) do not appear - they cancelled out. Settled 19 Apr 2026.
A16: Trademax NZ Limited | B16: 2026-04-30 | D16: 475.51 | F16: 'Outstanding statement as at 30 April 2026 - $475.51 Balance due'. Equals invoice 5653. Settled 18 May 2026.
A17: Trademax NZ Limited | B17: 2026-05-31 | D17: 588 | F17: 'Outstanding statement as at 31 May 2026 - $588.00 Balance due'. Equals invoice WAN6330. Settled 1 Jul 2026.
A18: Trademax NZ Limited | B18: 2026-06-30 | D18: 935.9 | E18: 588 | F18: 'Outstanding statement as at 30 June 2026 - $935.90 Balance due, $588.00 Overdue'. Balance = WAN6330 588.00 (overdue, due 20 Jun) + WAN8213 294.45 + WAN7942 53.45. All three settled by 20 Jul 2026.
